{
    "0OQLX86W1PXLU0CRSWPE7L2UL1": [
        {
            "title": "",
            "image2": "https:\/\/imgcdn.kim\/pv\/341\/0OQLX86W1PXLU0CRSWPE7L2UL1.jpg",
            "sources": [
                {
                    "file": "\/pv\/hls\/0OQLX86W1PXLU0CRSWPE7L2UL1.m3u8?in=::7a7be28c41d967aa0cdb41179c873d09::1776361155::su",
                    "label": "Auto",
                    "type": "application\/vnd.apple.mpegurl"
                },
                {
                    "file": "\/pv\/hls\/0OQLX86W1PXLU0CRSWPE7L2UL1.m3u8?q=1080p&in=::7a7be28c41d967aa0cdb41179c873d09::1776361155::su",
                    "label": "Full HD",
                    "type": "application\/vnd.apple.mpegurl"
                },
                {
                    "file": "\/pv\/hls\/0OQLX86W1PXLU0CRSWPE7L2UL1.m3u8?q=720p&in=::7a7be28c41d967aa0cdb41179c873d09::1776361155::su",
                    "label": "Mid HD",
                    "type": "application\/vnd.apple.mpegurl",
                    "default": "true"
                },
                {
                    "file": "\/pv\/hls\/0OQLX86W1PXLU0CRSWPE7L2UL1.m3u8?q=480p&in=::7a7be28c41d967aa0cdb41179c873d09::1776361155::su",
                    "label": "Low HD",
                    "type": "application\/vnd.apple.mpegurl"
                }
            ],
            "tracks": [
                {
                    "kind": "captions",
                    "file": "\/\/pv.subscdn.top\/subs\/0OQLX86W1PXLU0CRSWPE7L2UL1\/ms-bn.srt",
                    "label": "ms-bn"
                },
                {
                    "kind": "captions",
                    "file": "\/\/pv.subscdn.top\/subs\/0OQLX86W1PXLU0CRSWPE7L2UL1\/ms-my.srt",
                    "label": "ms-my"
                },
                {
                    "kind": "captions",
                    "file": "\/\/pv.subscdn.top\/subs\/0OQLX86W1PXLU0CRSWPE7L2UL1\/en-us.srt",
                    "label": "en-us"
                },
                {
                    "kind": "captions",
                    "file": "\/\/pv.subscdn.top\/subs\/0OQLX86W1PXLU0CRSWPE7L2UL1\/fr-fr.srt",
                    "label": "fr-fr"
                },
                {
                    "kind": "captions",
                    "file": "\/\/pv.subscdn.top\/subs\/0OQLX86W1PXLU0CRSWPE7L2UL1\/it-it.srt",
                    "label": "it-it"
                },
                {
                    "kind": "captions",
                    "file": "\/\/pv.subscdn.top\/subs\/0OQLX86W1PXLU0CRSWPE7L2UL1\/ru-ru.srt",
                    "label": "ru-ru"
                },
                {
                    "kind": "captions",
                    "file": "\/\/pv.subscdn.top\/subs\/0OQLX86W1PXLU0CRSWPE7L2UL1\/ar-ae.srt",
                    "label": "ar-ae"
                },
                {
                    "kind": "captions",
                    "file": "\/\/pv.subscdn.top\/subs\/0OQLX86W1PXLU0CRSWPE7L2UL1\/th-th.srt",
                    "label": "th-th"
                }
            ],
            "image1": "https:\/\/imgcdn.kim\/pv\/c\/0OQLX86W1PXLU0CRSWPE7L2UL1.jpg"
        }
    ],
    "0GVRWVPYEWP2ISMP4M9H28TEKE": [
        {
            "title": "",
            "image2": "https:\/\/imgcdn.kim\/pv\/341\/0GVRWVPYEWP2ISMP4M9H28TEKE.jpg",
            "sources": [
                {
                    "file": "\/pv\/hls\/0GVRWVPYEWP2ISMP4M9H28TEKE.m3u8?in=::5f4cb56e11a9ae2959afc8b4c41e03c6::1776361155::su",
                    "label": "Auto",
                    "type": "application\/vnd.apple.mpegurl"
                },
                {
                    "file": "\/pv\/hls\/0GVRWVPYEWP2ISMP4M9H28TEKE.m3u8?q=1080p&in=::5f4cb56e11a9ae2959afc8b4c41e03c6::1776361155::su",
                    "label": "Full HD",
                    "type": "application\/vnd.apple.mpegurl"
                },
                {
                    "file": "\/pv\/hls\/0GVRWVPYEWP2ISMP4M9H28TEKE.m3u8?q=720p&in=::5f4cb56e11a9ae2959afc8b4c41e03c6::1776361155::su",
                    "label": "Mid HD",
                    "type": "application\/vnd.apple.mpegurl",
                    "default": "true"
                },
                {
                    "file": "\/pv\/hls\/0GVRWVPYEWP2ISMP4M9H28TEKE.m3u8?q=480p&in=::5f4cb56e11a9ae2959afc8b4c41e03c6::1776361155::su",
                    "label": "Low HD",
                    "type": "application\/vnd.apple.mpegurl"
                }
            ],
            "tracks": [
                {
                    "kind": "captions",
                    "file": "\/\/pv.subscdn.top\/subs\/0GVRWVPYEWP2ISMP4M9H28TEKE\/en-us.[CC].srt",
                    "label": "en-us.[CC]"
                },
                {
                    "kind": "captions",
                    "file": "\/\/pv.subscdn.top\/subs\/0GVRWVPYEWP2ISMP4M9H28TEKE\/kn-in.[CC].srt",
                    "label": "kn-in.[CC]"
                }
            ],
            "image1": "https:\/\/imgcdn.kim\/pv\/c\/0GVRWVPYEWP2ISMP4M9H28TEKE.jpg"
        }
    ],
    "0PYOHW8F94U6Z8IOA12OUWUY0Q": [
        {
            "title": "",
            "image2": "https:\/\/imgcdn.kim\/pv\/341\/0PYOHW8F94U6Z8IOA12OUWUY0Q.jpg",
            "sources": [
                {
                    "file": "\/pv\/hls\/0PYOHW8F94U6Z8IOA12OUWUY0Q.m3u8?in=::d2e24ee8b2f2577d1d883f3e06589ad5::1776361156::su",
                    "label": "Auto",
                    "type": "application\/vnd.apple.mpegurl"
                },
                {
                    "file": "\/pv\/hls\/0PYOHW8F94U6Z8IOA12OUWUY0Q.m3u8?q=1080p&in=::d2e24ee8b2f2577d1d883f3e06589ad5::1776361156::su",
                    "label": "Full HD",
                    "type": "application\/vnd.apple.mpegurl"
                },
                {
                    "file": "\/pv\/hls\/0PYOHW8F94U6Z8IOA12OUWUY0Q.m3u8?q=720p&in=::d2e24ee8b2f2577d1d883f3e06589ad5::1776361156::su",
                    "label": "Mid HD",
                    "type": "application\/vnd.apple.mpegurl",
                    "default": "true"
                },
                {
                    "file": "\/pv\/hls\/0PYOHW8F94U6Z8IOA12OUWUY0Q.m3u8?q=480p&in=::d2e24ee8b2f2577d1d883f3e06589ad5::1776361156::su",
                    "label": "Low HD",
                    "type": "application\/vnd.apple.mpegurl"
                }
            ],
            "tracks": [
                {
                    "kind": "captions",
                    "file": "\/\/pv.subscdn.top\/subs\/0PYOHW8F94U6Z8IOA12OUWUY0Q\/ms-bn.srt",
                    "label": "ms-bn"
                },
                {
                    "kind": "captions",
                    "file": "\/\/pv.subscdn.top\/subs\/0PYOHW8F94U6Z8IOA12OUWUY0Q\/ms-my.srt",
                    "label": "ms-my"
                },
                {
                    "kind": "captions",
                    "file": "\/\/pv.subscdn.top\/subs\/0PYOHW8F94U6Z8IOA12OUWUY0Q\/en-us.srt",
                    "label": "en-us"
                },
                {
                    "kind": "captions",
                    "file": "\/\/pv.subscdn.top\/subs\/0PYOHW8F94U6Z8IOA12OUWUY0Q\/en-us.[CC].srt",
                    "label": "en-us.[CC]"
                },
                {
                    "kind": "captions",
                    "file": "\/\/pv.subscdn.top\/subs\/0PYOHW8F94U6Z8IOA12OUWUY0Q\/fr-fr.srt",
                    "label": "fr-fr"
                },
                {
                    "kind": "captions",
                    "file": "\/\/pv.subscdn.top\/subs\/0PYOHW8F94U6Z8IOA12OUWUY0Q\/cs-cz.srt",
                    "label": "cs-cz"
                },
                {
                    "kind": "captions",
                    "file": "\/\/pv.subscdn.top\/subs\/0PYOHW8F94U6Z8IOA12OUWUY0Q\/ru-ru.srt",
                    "label": "ru-ru"
                },
                {
                    "kind": "captions",
                    "file": "\/\/pv.subscdn.top\/subs\/0PYOHW8F94U6Z8IOA12OUWUY0Q\/ar-ae.srt",
                    "label": "ar-ae"
                },
                {
                    "kind": "captions",
                    "file": "\/\/pv.subscdn.top\/subs\/0PYOHW8F94U6Z8IOA12OUWUY0Q\/th-th.srt",
                    "label": "th-th"
                }
            ],
            "image1": "https:\/\/imgcdn.kim\/pv\/c\/0PYOHW8F94U6Z8IOA12OUWUY0Q.jpg"
        }
    ],
    "0S6YSCL5SYXZLPWB9JZUEQCB12": [
        {
            "title": "",
            "image2": "https:\/\/imgcdn.kim\/pv\/341\/0S6YSCL5SYXZLPWB9JZUEQCB12.jpg",
            "sources": [
                {
                    "file": "\/pv\/hls\/0S6YSCL5SYXZLPWB9JZUEQCB12.m3u8?in=::7f7330cf451deb6cf91ee899a2eca02e::1776361156::su",
                    "label": "Auto",
                    "type": "application\/vnd.apple.mpegurl"
                },
                {
                    "file": "\/pv\/hls\/0S6YSCL5SYXZLPWB9JZUEQCB12.m3u8?q=1080p&in=::7f7330cf451deb6cf91ee899a2eca02e::1776361156::su",
                    "label": "Full HD",
                    "type": "application\/vnd.apple.mpegurl"
                },
                {
                    "file": "\/pv\/hls\/0S6YSCL5SYXZLPWB9JZUEQCB12.m3u8?q=720p&in=::7f7330cf451deb6cf91ee899a2eca02e::1776361156::su",
                    "label": "Mid HD",
                    "type": "application\/vnd.apple.mpegurl",
                    "default": "true"
                },
                {
                    "file": "\/pv\/hls\/0S6YSCL5SYXZLPWB9JZUEQCB12.m3u8?q=480p&in=::7f7330cf451deb6cf91ee899a2eca02e::1776361156::su",
                    "label": "Low HD",
                    "type": "application\/vnd.apple.mpegurl"
                }
            ],
            "tracks": [
                {
                    "kind": "captions",
                    "file": "\/\/pv.subscdn.top\/subs\/0S6YSCL5SYXZLPWB9JZUEQCB12\/en-in.[CC].srt",
                    "label": "en-in.[CC]"
                }
            ],
            "image1": "https:\/\/imgcdn.kim\/pv\/c\/0S6YSCL5SYXZLPWB9JZUEQCB12.jpg"
        }
    ],
    "0LVYNT5KXCNRBLPRGJRGV8B8M4": [
        {
            "title": "",
            "image2": "https:\/\/imgcdn.kim\/pv\/341\/0LVYNT5KXCNRBLPRGJRGV8B8M4.jpg",
            "sources": [
                {
                    "file": "\/pv\/hls\/0LVYNT5KXCNRBLPRGJRGV8B8M4.m3u8?in=::88adaa8320f8689d7fee62a7e13ea8aa::1776361157::su",
                    "label": "Auto",
                    "type": "application\/vnd.apple.mpegurl"
                },
                {
                    "file": "\/pv\/hls\/0LVYNT5KXCNRBLPRGJRGV8B8M4.m3u8?q=1080p&in=::88adaa8320f8689d7fee62a7e13ea8aa::1776361157::su",
                    "label": "Full HD",
                    "type": "application\/vnd.apple.mpegurl"
                },
                {
                    "file": "\/pv\/hls\/0LVYNT5KXCNRBLPRGJRGV8B8M4.m3u8?q=720p&in=::88adaa8320f8689d7fee62a7e13ea8aa::1776361157::su",
                    "label": "Mid HD",
                    "type": "application\/vnd.apple.mpegurl",
                    "default": "true"
                },
                {
                    "file": "\/pv\/hls\/0LVYNT5KXCNRBLPRGJRGV8B8M4.m3u8?q=480p&in=::88adaa8320f8689d7fee62a7e13ea8aa::1776361157::su",
                    "label": "Low HD",
                    "type": "application\/vnd.apple.mpegurl"
                }
            ],
            "tracks": [
                {
                    "kind": "captions",
                    "file": "\/\/pv.subscdn.top\/subs\/0LVYNT5KXCNRBLPRGJRGV8B8M4\/en-in.[CC].srt",
                    "label": "en-in.[CC]"
                }
            ],
            "image1": "https:\/\/imgcdn.kim\/pv\/c\/0LVYNT5KXCNRBLPRGJRGV8B8M4.jpg"
        }
    ],
    "0M8N73XZTLEV0NCC3RVPXZG7SU": [
        {
            "title": "",
            "image2": "https:\/\/imgcdn.kim\/pv\/341\/0M8N73XZTLEV0NCC3RVPXZG7SU.jpg",
            "sources": [
                {
                    "file": "\/pv\/hls\/0M8N73XZTLEV0NCC3RVPXZG7SU.m3u8?in=::5faf0b33f78f17318f666fdd93ba8593::1776361157::su",
                    "label": "Auto",
                    "type": "application\/vnd.apple.mpegurl"
                },
                {
                    "file": "\/pv\/hls\/0M8N73XZTLEV0NCC3RVPXZG7SU.m3u8?q=1080p&in=::5faf0b33f78f17318f666fdd93ba8593::1776361157::su",
                    "label": "Full HD",
                    "type": "application\/vnd.apple.mpegurl"
                },
                {
                    "file": "\/pv\/hls\/0M8N73XZTLEV0NCC3RVPXZG7SU.m3u8?q=720p&in=::5faf0b33f78f17318f666fdd93ba8593::1776361157::su",
                    "label": "Mid HD",
                    "type": "application\/vnd.apple.mpegurl",
                    "default": "true"
                },
                {
                    "file": "\/pv\/hls\/0M8N73XZTLEV0NCC3RVPXZG7SU.m3u8?q=480p&in=::5faf0b33f78f17318f666fdd93ba8593::1776361157::su",
                    "label": "Low HD",
                    "type": "application\/vnd.apple.mpegurl"
                }
            ],
            "tracks": [
                {
                    "kind": "captions",
                    "file": "\/\/pv.subscdn.top\/subs\/0M8N73XZTLEV0NCC3RVPXZG7SU\/en-in.[CC].srt",
                    "label": "en-in.[CC]"
                }
            ],
            "image1": "https:\/\/imgcdn.kim\/pv\/c\/0M8N73XZTLEV0NCC3RVPXZG7SU.jpg"
        }
    ],
    "0RCHBQ2QLZ7G1JJA1TZUY04R42": [
        {
            "title": "",
            "image2": "https:\/\/imgcdn.kim\/pv\/341\/0RCHBQ2QLZ7G1JJA1TZUY04R42.jpg",
            "sources": [
                {
                    "file": "\/pv\/hls\/0RCHBQ2QLZ7G1JJA1TZUY04R42.m3u8?in=::71750b7e181cab4eef9ba341b1fc7c87::1776361157::su",
                    "label": "Auto",
                    "type": "application\/vnd.apple.mpegurl"
                },
                {
                    "file": "\/pv\/hls\/0RCHBQ2QLZ7G1JJA1TZUY04R42.m3u8?q=1080p&in=::71750b7e181cab4eef9ba341b1fc7c87::1776361157::su",
                    "label": "Full HD",
                    "type": "application\/vnd.apple.mpegurl"
                },
                {
                    "file": "\/pv\/hls\/0RCHBQ2QLZ7G1JJA1TZUY04R42.m3u8?q=720p&in=::71750b7e181cab4eef9ba341b1fc7c87::1776361157::su",
                    "label": "Mid HD",
                    "type": "application\/vnd.apple.mpegurl",
                    "default": "true"
                },
                {
                    "file": "\/pv\/hls\/0RCHBQ2QLZ7G1JJA1TZUY04R42.m3u8?q=480p&in=::71750b7e181cab4eef9ba341b1fc7c87::1776361157::su",
                    "label": "Low HD",
                    "type": "application\/vnd.apple.mpegurl"
                }
            ],
            "tracks": [
                {
                    "kind": "captions",
                    "file": "\/\/pv.subscdn.top\/subs\/0RCHBQ2QLZ7G1JJA1TZUY04R42\/en-us.[CC].srt",
                    "label": "en-us.[CC]"
                }
            ],
            "image1": "https:\/\/imgcdn.kim\/pv\/c\/0RCHBQ2QLZ7G1JJA1TZUY04R42.jpg"
        }
    ],
    "0JHIDTQXU9YR2YB9R73LY4WQ5M": [
        {
            "title": "",
            "image2": "https:\/\/imgcdn.kim\/pv\/341\/0JHIDTQXU9YR2YB9R73LY4WQ5M.jpg",
            "sources": [
                {
                    "file": "\/pv\/hls\/0JHIDTQXU9YR2YB9R73LY4WQ5M.m3u8?in=::42ae68e092c856b5a27e8a02a85ed5a1::1776361158::su",
                    "label": "Auto",
                    "type": "application\/vnd.apple.mpegurl"
                },
                {
                    "file": "\/pv\/hls\/0JHIDTQXU9YR2YB9R73LY4WQ5M.m3u8?q=1080p&in=::42ae68e092c856b5a27e8a02a85ed5a1::1776361158::su",
                    "label": "Full HD",
                    "type": "application\/vnd.apple.mpegurl"
                },
                {
                    "file": "\/pv\/hls\/0JHIDTQXU9YR2YB9R73LY4WQ5M.m3u8?q=720p&in=::42ae68e092c856b5a27e8a02a85ed5a1::1776361158::su",
                    "label": "Mid HD",
                    "type": "application\/vnd.apple.mpegurl",
                    "default": "true"
                },
                {
                    "file": "\/pv\/hls\/0JHIDTQXU9YR2YB9R73LY4WQ5M.m3u8?q=480p&in=::42ae68e092c856b5a27e8a02a85ed5a1::1776361158::su",
                    "label": "Low HD",
                    "type": "application\/vnd.apple.mpegurl"
                }
            ],
            "tracks": [
                {
                    "kind": "captions",
                    "file": "\/\/pv.subscdn.top\/subs\/0JHIDTQXU9YR2YB9R73LY4WQ5M\/da-dk.srt",
                    "label": "da-dk"
                },
                {
                    "kind": "captions",
                    "file": "\/\/pv.subscdn.top\/subs\/0JHIDTQXU9YR2YB9R73LY4WQ5M\/de-de.srt",
                    "label": "de-de"
                },
                {
                    "kind": "captions",
                    "file": "\/\/pv.subscdn.top\/subs\/0JHIDTQXU9YR2YB9R73LY4WQ5M\/en-us.[CC].srt",
                    "label": "en-us.[CC]"
                },
                {
                    "kind": "captions",
                    "file": "\/\/pv.subscdn.top\/subs\/0JHIDTQXU9YR2YB9R73LY4WQ5M\/es-es.srt",
                    "label": "es-es"
                },
                {
                    "kind": "captions",
                    "file": "\/\/pv.subscdn.top\/subs\/0JHIDTQXU9YR2YB9R73LY4WQ5M\/es-419.srt",
                    "label": "es-419"
                },
                {
                    "kind": "captions",
                    "file": "\/\/pv.subscdn.top\/subs\/0JHIDTQXU9YR2YB9R73LY4WQ5M\/fr-fr.srt",
                    "label": "fr-fr"
                },
                {
                    "kind": "captions",
                    "file": "\/\/pv.subscdn.top\/subs\/0JHIDTQXU9YR2YB9R73LY4WQ5M\/it-it.srt",
                    "label": "it-it"
                },
                {
                    "kind": "captions",
                    "file": "\/\/pv.subscdn.top\/subs\/0JHIDTQXU9YR2YB9R73LY4WQ5M\/nl-nl.srt",
                    "label": "nl-nl"
                },
                {
                    "kind": "captions",
                    "file": "\/\/pv.subscdn.top\/subs\/0JHIDTQXU9YR2YB9R73LY4WQ5M\/nb-no.srt",
                    "label": "nb-no"
                },
                {
                    "kind": "captions",
                    "file": "\/\/pv.subscdn.top\/subs\/0JHIDTQXU9YR2YB9R73LY4WQ5M\/pl-pl.srt",
                    "label": "pl-pl"
                },
                {
                    "kind": "captions",
                    "file": "\/\/pv.subscdn.top\/subs\/0JHIDTQXU9YR2YB9R73LY4WQ5M\/pt-br.srt",
                    "label": "pt-br"
                },
                {
                    "kind": "captions",
                    "file": "\/\/pv.subscdn.top\/subs\/0JHIDTQXU9YR2YB9R73LY4WQ5M\/pt-pt.srt",
                    "label": "pt-pt"
                },
                {
                    "kind": "captions",
                    "file": "\/\/pv.subscdn.top\/subs\/0JHIDTQXU9YR2YB9R73LY4WQ5M\/fi-fi.srt",
                    "label": "fi-fi"
                },
                {
                    "kind": "captions",
                    "file": "\/\/pv.subscdn.top\/subs\/0JHIDTQXU9YR2YB9R73LY4WQ5M\/sv-se.srt",
                    "label": "sv-se"
                },
                {
                    "kind": "captions",
                    "file": "\/\/pv.subscdn.top\/subs\/0JHIDTQXU9YR2YB9R73LY4WQ5M\/tr-tr.srt",
                    "label": "tr-tr"
                },
                {
                    "kind": "captions",
                    "file": "\/\/pv.subscdn.top\/subs\/0JHIDTQXU9YR2YB9R73LY4WQ5M\/ja-jp.srt",
                    "label": "ja-jp"
                }
            ],
            "image1": "https:\/\/imgcdn.kim\/pv\/c\/0JHIDTQXU9YR2YB9R73LY4WQ5M.jpg"
        }
    ],
    "0IS7PNM5KQL5PF2W9CTOJX9DTA": [
        {
            "title": "",
            "image2": "https:\/\/imgcdn.kim\/pv\/341\/0IS7PNM5KQL5PF2W9CTOJX9DTA.jpg",
            "sources": [
                {
                    "file": "\/pv\/hls\/0IS7PNM5KQL5PF2W9CTOJX9DTA.m3u8?in=::a4fc4db41c05c8d43793e70cf9f5c577::1776361158::su",
                    "label": "Auto",
                    "type": "application\/vnd.apple.mpegurl"
                },
                {
                    "file": "\/pv\/hls\/0IS7PNM5KQL5PF2W9CTOJX9DTA.m3u8?q=1080p&in=::a4fc4db41c05c8d43793e70cf9f5c577::1776361158::su",
                    "label": "Full HD",
                    "type": "application\/vnd.apple.mpegurl"
                },
                {
                    "file": "\/pv\/hls\/0IS7PNM5KQL5PF2W9CTOJX9DTA.m3u8?q=720p&in=::a4fc4db41c05c8d43793e70cf9f5c577::1776361158::su",
                    "label": "Mid HD",
                    "type": "application\/vnd.apple.mpegurl",
                    "default": "true"
                },
                {
                    "file": "\/pv\/hls\/0IS7PNM5KQL5PF2W9CTOJX9DTA.m3u8?q=480p&in=::a4fc4db41c05c8d43793e70cf9f5c577::1776361158::su",
                    "label": "Low HD",
                    "type": "application\/vnd.apple.mpegurl"
                }
            ],
            "tracks": [
                {
                    "kind": "captions",
                    "file": "\/\/pv.subscdn.top\/subs\/0IS7PNM5KQL5PF2W9CTOJX9DTA\/en-us.[CC].srt",
                    "label": "en-us.[CC]"
                }
            ],
            "image1": "https:\/\/imgcdn.kim\/pv\/c\/0IS7PNM5KQL5PF2W9CTOJX9DTA.jpg"
        }
    ],
    "0JGCYDU9TH2QWRZ5S98H4BYCXN": [
        {
            "title": "",
            "image2": "https:\/\/imgcdn.kim\/pv\/341\/0JGCYDU9TH2QWRZ5S98H4BYCXN.jpg",
            "sources": [
                {
                    "file": "\/pv\/hls\/0JGCYDU9TH2QWRZ5S98H4BYCXN.m3u8?in=::647f076ce4b0034bbdb79d719fa51698::1776361159::su",
                    "label": "Auto",
                    "type": "application\/vnd.apple.mpegurl"
                },
                {
                    "file": "\/pv\/hls\/0JGCYDU9TH2QWRZ5S98H4BYCXN.m3u8?q=1080p&in=::647f076ce4b0034bbdb79d719fa51698::1776361159::su",
                    "label": "Full HD",
                    "type": "application\/vnd.apple.mpegurl"
                },
                {
                    "file": "\/pv\/hls\/0JGCYDU9TH2QWRZ5S98H4BYCXN.m3u8?q=720p&in=::647f076ce4b0034bbdb79d719fa51698::1776361159::su",
                    "label": "Mid HD",
                    "type": "application\/vnd.apple.mpegurl",
                    "default": "true"
                },
                {
                    "file": "\/pv\/hls\/0JGCYDU9TH2QWRZ5S98H4BYCXN.m3u8?q=480p&in=::647f076ce4b0034bbdb79d719fa51698::1776361159::su",
                    "label": "Low HD",
                    "type": "application\/vnd.apple.mpegurl"
                }
            ],
            "tracks": [
                {
                    "kind": "captions",
                    "file": "\/\/pv.subscdn.top\/subs\/0JGCYDU9TH2QWRZ5S98H4BYCXN\/en-us.[CC].srt",
                    "label": "en-us.[CC]"
                }
            ],
            "image1": "https:\/\/imgcdn.kim\/pv\/c\/0JGCYDU9TH2QWRZ5S98H4BYCXN.jpg"
        }
    ],
    "0I1BA6T5B06IXBUGRXNKOKZVIU": [
        {
            "title": "",
            "image2": "https:\/\/imgcdn.kim\/pv\/341\/0I1BA6T5B06IXBUGRXNKOKZVIU.jpg",
            "sources": [
                {
                    "file": "\/pv\/hls\/0I1BA6T5B06IXBUGRXNKOKZVIU.m3u8?in=::6b88690bc321228687e6c1ab58be7bbd::1776361159::su",
                    "label": "Auto",
                    "type": "application\/vnd.apple.mpegurl"
                },
                {
                    "file": "\/pv\/hls\/0I1BA6T5B06IXBUGRXNKOKZVIU.m3u8?q=1080p&in=::6b88690bc321228687e6c1ab58be7bbd::1776361159::su",
                    "label": "Full HD",
                    "type": "application\/vnd.apple.mpegurl"
                },
                {
                    "file": "\/pv\/hls\/0I1BA6T5B06IXBUGRXNKOKZVIU.m3u8?q=720p&in=::6b88690bc321228687e6c1ab58be7bbd::1776361159::su",
                    "label": "Mid HD",
                    "type": "application\/vnd.apple.mpegurl",
                    "default": "true"
                },
                {
                    "file": "\/pv\/hls\/0I1BA6T5B06IXBUGRXNKOKZVIU.m3u8?q=480p&in=::6b88690bc321228687e6c1ab58be7bbd::1776361159::su",
                    "label": "Low HD",
                    "type": "application\/vnd.apple.mpegurl"
                }
            ],
            "tracks": [
                {
                    "kind": "captions",
                    "file": "\/\/pv.subscdn.top\/subs\/0I1BA6T5B06IXBUGRXNKOKZVIU\/en-us.[CC].srt",
                    "label": "en-us.[CC]"
                }
            ],
            "image1": "https:\/\/imgcdn.kim\/pv\/c\/0I1BA6T5B06IXBUGRXNKOKZVIU.jpg"
        }
    ],
    "0KX27B947OXMOK6TA5V0B569HU": [
        {
            "title": "",
            "image2": "https:\/\/imgcdn.kim\/pv\/341\/0KX27B947OXMOK6TA5V0B569HU.jpg",
            "sources": [
                {
                    "file": "\/pv\/hls\/0KX27B947OXMOK6TA5V0B569HU.m3u8?in=::96cd3cd78424125e226178c192f81f10::1776361159::su",
                    "label": "Auto",
                    "type": "application\/vnd.apple.mpegurl"
                },
                {
                    "file": "\/pv\/hls\/0KX27B947OXMOK6TA5V0B569HU.m3u8?q=1080p&in=::96cd3cd78424125e226178c192f81f10::1776361159::su",
                    "label": "Full HD",
                    "type": "application\/vnd.apple.mpegurl"
                },
                {
                    "file": "\/pv\/hls\/0KX27B947OXMOK6TA5V0B569HU.m3u8?q=720p&in=::96cd3cd78424125e226178c192f81f10::1776361159::su",
                    "label": "Mid HD",
                    "type": "application\/vnd.apple.mpegurl",
                    "default": "true"
                },
                {
                    "file": "\/pv\/hls\/0KX27B947OXMOK6TA5V0B569HU.m3u8?q=480p&in=::96cd3cd78424125e226178c192f81f10::1776361159::su",
                    "label": "Low HD",
                    "type": "application\/vnd.apple.mpegurl"
                }
            ],
            "tracks": [
                {
                    "kind": "captions",
                    "file": "\/\/pv.subscdn.top\/subs\/0KX27B947OXMOK6TA5V0B569HU\/en-in.[CC].srt",
                    "label": "en-in.[CC]"
                }
            ],
            "image1": "https:\/\/imgcdn.kim\/pv\/c\/0KX27B947OXMOK6TA5V0B569HU.jpg"
        }
    ],
    "0L9MLSGLI35XQAAI93H02DIZA7": [
        {
            "title": "",
            "image2": "https:\/\/imgcdn.kim\/pv\/341\/0L9MLSGLI35XQAAI93H02DIZA7.jpg",
            "sources": [
                {
                    "file": "\/pv\/hls\/0L9MLSGLI35XQAAI93H02DIZA7.m3u8?in=::6f71fcfdd38ef4ba7fe534ca97fe683b::1776361160::su",
                    "label": "Auto",
                    "type": "application\/vnd.apple.mpegurl"
                },
                {
                    "file": "\/pv\/hls\/0L9MLSGLI35XQAAI93H02DIZA7.m3u8?q=1080p&in=::6f71fcfdd38ef4ba7fe534ca97fe683b::1776361160::su",
                    "label": "Full HD",
                    "type": "application\/vnd.apple.mpegurl"
                },
                {
                    "file": "\/pv\/hls\/0L9MLSGLI35XQAAI93H02DIZA7.m3u8?q=720p&in=::6f71fcfdd38ef4ba7fe534ca97fe683b::1776361160::su",
                    "label": "Mid HD",
                    "type": "application\/vnd.apple.mpegurl",
                    "default": "true"
                },
                {
                    "file": "\/pv\/hls\/0L9MLSGLI35XQAAI93H02DIZA7.m3u8?q=480p&in=::6f71fcfdd38ef4ba7fe534ca97fe683b::1776361160::su",
                    "label": "Low HD",
                    "type": "application\/vnd.apple.mpegurl"
                }
            ],
            "tracks": [
                {
                    "kind": "captions",
                    "file": "\/\/pv.subscdn.top\/subs\/0L9MLSGLI35XQAAI93H02DIZA7\/en-gb.[CC].srt",
                    "label": "en-gb.[CC]"
                },
                {
                    "kind": "captions",
                    "file": "\/\/pv.subscdn.top\/subs\/0L9MLSGLI35XQAAI93H02DIZA7\/ta-in.[CC].srt",
                    "label": "ta-in.[CC]"
                }
            ],
            "image1": "https:\/\/imgcdn.kim\/pv\/c\/0L9MLSGLI35XQAAI93H02DIZA7.jpg"
        }
    ],
    "0PLJTEWLG7TYAKQ9FBK5G7DAH5": [
        {
            "title": "",
            "image2": "https:\/\/imgcdn.kim\/pv\/341\/0PLJTEWLG7TYAKQ9FBK5G7DAH5.jpg",
            "sources": [
                {
                    "file": "\/pv\/hls\/0PLJTEWLG7TYAKQ9FBK5G7DAH5.m3u8?in=::b8d4a32223b931d74ea3d9356b261a8d::1776361160::su",
                    "label": "Auto",
                    "type": "application\/vnd.apple.mpegurl"
                },
                {
                    "file": "\/pv\/hls\/0PLJTEWLG7TYAKQ9FBK5G7DAH5.m3u8?q=1080p&in=::b8d4a32223b931d74ea3d9356b261a8d::1776361160::su",
                    "label": "Full HD",
                    "type": "application\/vnd.apple.mpegurl"
                },
                {
                    "file": "\/pv\/hls\/0PLJTEWLG7TYAKQ9FBK5G7DAH5.m3u8?q=720p&in=::b8d4a32223b931d74ea3d9356b261a8d::1776361160::su",
                    "label": "Mid HD",
                    "type": "application\/vnd.apple.mpegurl",
                    "default": "true"
                },
                {
                    "file": "\/pv\/hls\/0PLJTEWLG7TYAKQ9FBK5G7DAH5.m3u8?q=480p&in=::b8d4a32223b931d74ea3d9356b261a8d::1776361160::su",
                    "label": "Low HD",
                    "type": "application\/vnd.apple.mpegurl"
                }
            ],
            "tracks": [
                {
                    "kind": "captions",
                    "file": "\/\/pv.subscdn.top\/subs\/0PLJTEWLG7TYAKQ9FBK5G7DAH5\/en-in.[CC].srt",
                    "label": "en-in.[CC]"
                }
            ],
            "image1": "https:\/\/imgcdn.kim\/pv\/c\/0PLJTEWLG7TYAKQ9FBK5G7DAH5.jpg"
        }
    ],
    "0QFLNUY6QR5GEV4SZD4FGJ8T6B": [
        {
            "title": "",
            "image2": "https:\/\/imgcdn.kim\/pv\/341\/0QFLNUY6QR5GEV4SZD4FGJ8T6B.jpg",
            "sources": [
                {
                    "file": "\/pv\/hls\/0QFLNUY6QR5GEV4SZD4FGJ8T6B.m3u8?in=::7ddd991d5d599b2997ebc7845dc4e451::1776361161::su",
                    "label": "Auto",
                    "type": "application\/vnd.apple.mpegurl"
                },
                {
                    "file": "\/pv\/hls\/0QFLNUY6QR5GEV4SZD4FGJ8T6B.m3u8?q=1080p&in=::7ddd991d5d599b2997ebc7845dc4e451::1776361161::su",
                    "label": "Full HD",
                    "type": "application\/vnd.apple.mpegurl"
                },
                {
                    "file": "\/pv\/hls\/0QFLNUY6QR5GEV4SZD4FGJ8T6B.m3u8?q=720p&in=::7ddd991d5d599b2997ebc7845dc4e451::1776361161::su",
                    "label": "Mid HD",
                    "type": "application\/vnd.apple.mpegurl",
                    "default": "true"
                },
                {
                    "file": "\/pv\/hls\/0QFLNUY6QR5GEV4SZD4FGJ8T6B.m3u8?q=480p&in=::7ddd991d5d599b2997ebc7845dc4e451::1776361161::su",
                    "label": "Low HD",
                    "type": "application\/vnd.apple.mpegurl"
                }
            ],
            "tracks": [
                {
                    "kind": "captions",
                    "file": "\/\/pv.subscdn.top\/subs\/0QFLNUY6QR5GEV4SZD4FGJ8T6B\/en-us.[CC].srt",
                    "label": "en-us.[CC]"
                }
            ],
            "image1": "https:\/\/imgcdn.kim\/pv\/c\/0QFLNUY6QR5GEV4SZD4FGJ8T6B.jpg"
        }
    ],
    "0PTRLJ933K9LLB5VMRK231PFYP": [
        {
            "title": "",
            "image2": "https:\/\/imgcdn.kim\/pv\/341\/0PTRLJ933K9LLB5VMRK231PFYP.jpg",
            "sources": [
                {
                    "file": "\/pv\/hls\/0PTRLJ933K9LLB5VMRK231PFYP.m3u8?in=::52b4246275914f0db2c6832b8d56cae9::1776361161::su",
                    "label": "Auto",
                    "type": "application\/vnd.apple.mpegurl"
                },
                {
                    "file": "\/pv\/hls\/0PTRLJ933K9LLB5VMRK231PFYP.m3u8?q=1080p&in=::52b4246275914f0db2c6832b8d56cae9::1776361161::su",
                    "label": "Full HD",
                    "type": "application\/vnd.apple.mpegurl"
                },
                {
                    "file": "\/pv\/hls\/0PTRLJ933K9LLB5VMRK231PFYP.m3u8?q=720p&in=::52b4246275914f0db2c6832b8d56cae9::1776361161::su",
                    "label": "Mid HD",
                    "type": "application\/vnd.apple.mpegurl",
                    "default": "true"
                },
                {
                    "file": "\/pv\/hls\/0PTRLJ933K9LLB5VMRK231PFYP.m3u8?q=480p&in=::52b4246275914f0db2c6832b8d56cae9::1776361161::su",
                    "label": "Low HD",
                    "type": "application\/vnd.apple.mpegurl"
                }
            ],
            "tracks": [
                {
                    "kind": "captions",
                    "file": "\/\/pv.subscdn.top\/subs\/0PTRLJ933K9LLB5VMRK231PFYP\/en-us.[CC].srt",
                    "label": "en-us.[CC]"
                }
            ],
            "image1": "https:\/\/imgcdn.kim\/pv\/c\/0PTRLJ933K9LLB5VMRK231PFYP.jpg"
        }
    ],
    "0U7J59EKB5346WDOPFT462U406": [
        {
            "title": "",
            "image2": "https:\/\/imgcdn.kim\/pv\/341\/0U7J59EKB5346WDOPFT462U406.jpg",
            "sources": [
                {
                    "file": "\/pv\/hls\/0U7J59EKB5346WDOPFT462U406.m3u8?in=::cba1008154a56807781a54b6ef2b07b0::1776361161::su",
                    "label": "Auto",
                    "type": "application\/vnd.apple.mpegurl"
                },
                {
                    "file": "\/pv\/hls\/0U7J59EKB5346WDOPFT462U406.m3u8?q=1080p&in=::cba1008154a56807781a54b6ef2b07b0::1776361161::su",
                    "label": "Full HD",
                    "type": "application\/vnd.apple.mpegurl"
                },
                {
                    "file": "\/pv\/hls\/0U7J59EKB5346WDOPFT462U406.m3u8?q=720p&in=::cba1008154a56807781a54b6ef2b07b0::1776361161::su",
                    "label": "Mid HD",
                    "type": "application\/vnd.apple.mpegurl",
                    "default": "true"
                },
                {
                    "file": "\/pv\/hls\/0U7J59EKB5346WDOPFT462U406.m3u8?q=480p&in=::cba1008154a56807781a54b6ef2b07b0::1776361161::su",
                    "label": "Low HD",
                    "type": "application\/vnd.apple.mpegurl"
                }
            ],
            "tracks": [
                {
                    "kind": "captions",
                    "file": "\/\/pv.subscdn.top\/subs\/0U7J59EKB5346WDOPFT462U406\/en-us.srt",
                    "label": "en-us"
                },
                {
                    "kind": "captions",
                    "file": "\/\/pv.subscdn.top\/subs\/0U7J59EKB5346WDOPFT462U406\/hi-in.[CC].srt",
                    "label": "hi-in.[CC]"
                }
            ],
            "image1": "https:\/\/imgcdn.kim\/pv\/c\/0U7J59EKB5346WDOPFT462U406.jpg"
        }
    ],
    "0PE6PJJOQB76RJN80PPW03Z0MM": [
        {
            "title": "",
            "image2": "https:\/\/imgcdn.kim\/pv\/341\/0PE6PJJOQB76RJN80PPW03Z0MM.jpg",
            "sources": [
                {
                    "file": "\/pv\/hls\/0PE6PJJOQB76RJN80PPW03Z0MM.m3u8?in=::7c7bb9d102f0fca199a7f63ec3a534c5::1776361162::su",
                    "label": "Auto",
                    "type": "application\/vnd.apple.mpegurl"
                },
                {
                    "file": "\/pv\/hls\/0PE6PJJOQB76RJN80PPW03Z0MM.m3u8?q=1080p&in=::7c7bb9d102f0fca199a7f63ec3a534c5::1776361162::su",
                    "label": "Full HD",
                    "type": "application\/vnd.apple.mpegurl"
                },
                {
                    "file": "\/pv\/hls\/0PE6PJJOQB76RJN80PPW03Z0MM.m3u8?q=720p&in=::7c7bb9d102f0fca199a7f63ec3a534c5::1776361162::su",
                    "label": "Mid HD",
                    "type": "application\/vnd.apple.mpegurl",
                    "default": "true"
                },
                {
                    "file": "\/pv\/hls\/0PE6PJJOQB76RJN80PPW03Z0MM.m3u8?q=480p&in=::7c7bb9d102f0fca199a7f63ec3a534c5::1776361162::su",
                    "label": "Low HD",
                    "type": "application\/vnd.apple.mpegurl"
                }
            ],
            "tracks": [
                {
                    "kind": "captions",
                    "file": "\/\/pv.subscdn.top\/subs\/0PE6PJJOQB76RJN80PPW03Z0MM\/en-us.[CC].srt",
                    "label": "en-us.[CC]"
                }
            ],
            "image1": "https:\/\/imgcdn.kim\/pv\/c\/0PE6PJJOQB76RJN80PPW03Z0MM.jpg"
        }
    ],
    "0JOQU008BYGPG8CWQEA5NYG8KK": [
        {
            "title": "",
            "image2": "https:\/\/imgcdn.kim\/pv\/341\/0JOQU008BYGPG8CWQEA5NYG8KK.jpg",
            "sources": [
                {
                    "file": "\/pv\/hls\/0JOQU008BYGPG8CWQEA5NYG8KK.m3u8?in=::a1bc2b5326465340f322c7972f7c0bfd::1776361162::su",
                    "label": "Auto",
                    "type": "application\/vnd.apple.mpegurl"
                },
                {
                    "file": "\/pv\/hls\/0JOQU008BYGPG8CWQEA5NYG8KK.m3u8?q=1080p&in=::a1bc2b5326465340f322c7972f7c0bfd::1776361162::su",
                    "label": "Full HD",
                    "type": "application\/vnd.apple.mpegurl"
                },
                {
                    "file": "\/pv\/hls\/0JOQU008BYGPG8CWQEA5NYG8KK.m3u8?q=720p&in=::a1bc2b5326465340f322c7972f7c0bfd::1776361162::su",
                    "label": "Mid HD",
                    "type": "application\/vnd.apple.mpegurl",
                    "default": "true"
                },
                {
                    "file": "\/pv\/hls\/0JOQU008BYGPG8CWQEA5NYG8KK.m3u8?q=480p&in=::a1bc2b5326465340f322c7972f7c0bfd::1776361162::su",
                    "label": "Low HD",
                    "type": "application\/vnd.apple.mpegurl"
                }
            ],
            "tracks": [
                {
                    "kind": "captions",
                    "file": "\/\/pv.subscdn.top\/subs\/0JOQU008BYGPG8CWQEA5NYG8KK\/en-us.[CC].srt",
                    "label": "en-us.[CC]"
                }
            ],
            "image1": "https:\/\/imgcdn.kim\/pv\/c\/0JOQU008BYGPG8CWQEA5NYG8KK.jpg"
        }
    ],
    "0QJW06EHRF8JDFMNFUWBK5Z11K": [
        {
            "title": "",
            "image2": "https:\/\/imgcdn.kim\/pv\/341\/0QJW06EHRF8JDFMNFUWBK5Z11K.jpg",
            "sources": [
                {
                    "file": "\/pv\/hls\/0QJW06EHRF8JDFMNFUWBK5Z11K.m3u8?in=::131f2c29c1d9b882dc40c66c9d0c15c4::1776361163::su",
                    "label": "Auto",
                    "type": "application\/vnd.apple.mpegurl"
                },
                {
                    "file": "\/pv\/hls\/0QJW06EHRF8JDFMNFUWBK5Z11K.m3u8?q=1080p&in=::131f2c29c1d9b882dc40c66c9d0c15c4::1776361163::su",
                    "label": "Full HD",
                    "type": "application\/vnd.apple.mpegurl"
                },
                {
                    "file": "\/pv\/hls\/0QJW06EHRF8JDFMNFUWBK5Z11K.m3u8?q=720p&in=::131f2c29c1d9b882dc40c66c9d0c15c4::1776361163::su",
                    "label": "Mid HD",
                    "type": "application\/vnd.apple.mpegurl",
                    "default": "true"
                },
                {
                    "file": "\/pv\/hls\/0QJW06EHRF8JDFMNFUWBK5Z11K.m3u8?q=480p&in=::131f2c29c1d9b882dc40c66c9d0c15c4::1776361163::su",
                    "label": "Low HD",
                    "type": "application\/vnd.apple.mpegurl"
                }
            ],
            "tracks": [
                {
                    "kind": "captions",
                    "file": "\/\/pv.subscdn.top\/subs\/0QJW06EHRF8JDFMNFUWBK5Z11K\/en-in.[CC].srt",
                    "label": "en-in.[CC]"
                }
            ],
            "image1": "https:\/\/imgcdn.kim\/pv\/c\/0QJW06EHRF8JDFMNFUWBK5Z11K.jpg"
        }
    ],
    "0ODABDMCTTVX2548XNO73TZOU8": [
        {
            "title": "",
            "image2": "https:\/\/imgcdn.kim\/pv\/341\/0ODABDMCTTVX2548XNO73TZOU8.jpg",
            "sources": [
                {
                    "file": "\/pv\/hls\/0ODABDMCTTVX2548XNO73TZOU8.m3u8?in=::694506f1af92c45323057b103cf7fa4b::1776361163::su",
                    "label": "Auto",
                    "type": "application\/vnd.apple.mpegurl"
                },
                {
                    "file": "\/pv\/hls\/0ODABDMCTTVX2548XNO73TZOU8.m3u8?q=1080p&in=::694506f1af92c45323057b103cf7fa4b::1776361163::su",
                    "label": "Full HD",
                    "type": "application\/vnd.apple.mpegurl"
                },
                {
                    "file": "\/pv\/hls\/0ODABDMCTTVX2548XNO73TZOU8.m3u8?q=720p&in=::694506f1af92c45323057b103cf7fa4b::1776361163::su",
                    "label": "Mid HD",
                    "type": "application\/vnd.apple.mpegurl",
                    "default": "true"
                },
                {
                    "file": "\/pv\/hls\/0ODABDMCTTVX2548XNO73TZOU8.m3u8?q=480p&in=::694506f1af92c45323057b103cf7fa4b::1776361163::su",
                    "label": "Low HD",
                    "type": "application\/vnd.apple.mpegurl"
                }
            ],
            "tracks": [
                {
                    "kind": "captions",
                    "file": "\/\/pv.subscdn.top\/subs\/0ODABDMCTTVX2548XNO73TZOU8\/en-us.[CC].srt",
                    "label": "en-us.[CC]"
                }
            ],
            "image1": "https:\/\/imgcdn.kim\/pv\/c\/0ODABDMCTTVX2548XNO73TZOU8.jpg"
        }
    ],
    "0T5JHC3YBYO4DIK15PQEM55MZ6": [
        {
            "title": "",
            "image2": "https:\/\/imgcdn.kim\/pv\/341\/0T5JHC3YBYO4DIK15PQEM55MZ6.jpg",
            "sources": [
                {
                    "file": "\/pv\/hls\/0T5JHC3YBYO4DIK15PQEM55MZ6.m3u8?in=::d4ebf2ec9a62d79445672ad91ac01e02::1776361163::su",
                    "label": "Auto",
                    "type": "application\/vnd.apple.mpegurl"
                },
                {
                    "file": "\/pv\/hls\/0T5JHC3YBYO4DIK15PQEM55MZ6.m3u8?q=1080p&in=::d4ebf2ec9a62d79445672ad91ac01e02::1776361163::su",
                    "label": "Full HD",
                    "type": "application\/vnd.apple.mpegurl"
                },
                {
                    "file": "\/pv\/hls\/0T5JHC3YBYO4DIK15PQEM55MZ6.m3u8?q=720p&in=::d4ebf2ec9a62d79445672ad91ac01e02::1776361163::su",
                    "label": "Mid HD",
                    "type": "application\/vnd.apple.mpegurl",
                    "default": "true"
                },
                {
                    "file": "\/pv\/hls\/0T5JHC3YBYO4DIK15PQEM55MZ6.m3u8?q=480p&in=::d4ebf2ec9a62d79445672ad91ac01e02::1776361163::su",
                    "label": "Low HD",
                    "type": "application\/vnd.apple.mpegurl"
                }
            ],
            "tracks": [
                {
                    "kind": "captions",
                    "file": "\/\/pv.subscdn.top\/subs\/0T5JHC3YBYO4DIK15PQEM55MZ6\/en-us.[CC].srt",
                    "label": "en-us.[CC]"
                }
            ],
            "image1": "https:\/\/imgcdn.kim\/pv\/c\/0T5JHC3YBYO4DIK15PQEM55MZ6.jpg"
        }
    ]
}