{
    "0KH1P0M9EHSANCNW3WRJCLX7O7": [
        {
            "title": "",
            "image2": "https:\/\/imgcdn.kim\/pv\/341\/0KH1P0M9EHSANCNW3WRJCLX7O7.jpg",
            "sources": [
                {
                    "file": "\/pv\/hls\/0KH1P0M9EHSANCNW3WRJCLX7O7.m3u8?in=::2936282008ba3fed65a99eaced7658ef::1773442577::su",
                    "label": "Auto",
                    "type": "application\/vnd.apple.mpegurl"
                }
            ],
            "image1": "https:\/\/imgcdn.kim\/pv\/c\/0KH1P0M9EHSANCNW3WRJCLX7O7.jpg"
        }
    ],
    "0MCX9LB0YWVROU83ZL14346MH5": [
        {
            "title": "",
            "image2": "https:\/\/imgcdn.kim\/pv\/341\/0MCX9LB0YWVROU83ZL14346MH5.jpg",
            "sources": [
                {
                    "file": "\/pv\/hls\/0MCX9LB0YWVROU83ZL14346MH5.m3u8?in=::d93b8b3315abb28eb4dca75b15daaca2::1773442577::su",
                    "label": "Auto",
                    "type": "application\/vnd.apple.mpegurl"
                }
            ],
            "image1": "https:\/\/imgcdn.kim\/pv\/c\/0MCX9LB0YWVROU83ZL14346MH5.jpg"
        }
    ],
    "0S82NUVX2P943FDSDVD026QZHS": [
        {
            "title": "",
            "image2": "https:\/\/imgcdn.kim\/pv\/341\/0S82NUVX2P943FDSDVD026QZHS.jpg",
            "sources": [
                {
                    "file": "\/pv\/hls\/0S82NUVX2P943FDSDVD026QZHS.m3u8?in=::27e771e991d90d123196975e9838e928::1773442577::su",
                    "label": "Auto",
                    "type": "application\/vnd.apple.mpegurl"
                }
            ],
            "image1": "https:\/\/imgcdn.kim\/pv\/c\/0S82NUVX2P943FDSDVD026QZHS.jpg"
        }
    ],
    "0KA6HUP1RILKQD9JJNEABVXDPX": [
        {
            "title": "",
            "image2": "https:\/\/imgcdn.kim\/pv\/341\/0KA6HUP1RILKQD9JJNEABVXDPX.jpg",
            "sources": [
                {
                    "file": "\/pv\/hls\/0KA6HUP1RILKQD9JJNEABVXDPX.m3u8?in=::524b4360f2e5950308207de3d2da0d6b::1773442578::su",
                    "label": "Auto",
                    "type": "application\/vnd.apple.mpegurl"
                }
            ],
            "image1": "https:\/\/imgcdn.kim\/pv\/c\/0KA6HUP1RILKQD9JJNEABVXDPX.jpg"
        }
    ],
    "0L8WGN7EL0R0TKPNHZ0DETKJJG": [
        {
            "title": "",
            "image2": "https:\/\/imgcdn.kim\/pv\/341\/0L8WGN7EL0R0TKPNHZ0DETKJJG.jpg",
            "sources": [
                {
                    "file": "\/pv\/hls\/0L8WGN7EL0R0TKPNHZ0DETKJJG.m3u8?in=::d389dfccd11d465b01516cfccb03824e::1773442578::su",
                    "label": "Auto",
                    "type": "application\/vnd.apple.mpegurl"
                }
            ],
            "image1": "https:\/\/imgcdn.kim\/pv\/c\/0L8WGN7EL0R0TKPNHZ0DETKJJG.jpg"
        }
    ],
    "0K70YS9BGL76WWR8TQVK2VAR22": [
        {
            "title": "",
            "image2": "https:\/\/imgcdn.kim\/pv\/341\/0K70YS9BGL76WWR8TQVK2VAR22.jpg",
            "sources": [
                {
                    "file": "\/pv\/hls\/0K70YS9BGL76WWR8TQVK2VAR22.m3u8?in=::612ceebd7ba14842b7a8e973b6bf47ab::1773442578::su",
                    "label": "Auto",
                    "type": "application\/vnd.apple.mpegurl"
                }
            ],
            "image1": "https:\/\/imgcdn.kim\/pv\/c\/0K70YS9BGL76WWR8TQVK2VAR22.jpg"
        }
    ],
    "0N43EEHVHWN70WP69DWNP4QT87": [
        {
            "title": "",
            "image2": "https:\/\/imgcdn.kim\/pv\/341\/0N43EEHVHWN70WP69DWNP4QT87.jpg",
            "sources": [
                {
                    "file": "\/pv\/hls\/0N43EEHVHWN70WP69DWNP4QT87.m3u8?in=::a3a23be78510a216e53bf4f1f03e726a::1773442578::su",
                    "label": "Auto",
                    "type": "application\/vnd.apple.mpegurl"
                }
            ],
            "image1": "https:\/\/imgcdn.kim\/pv\/c\/0N43EEHVHWN70WP69DWNP4QT87.jpg"
        }
    ],
    "0SL0HAR0CG20THKIWQWYVCPQ20": [
        {
            "title": "",
            "image2": "https:\/\/imgcdn.kim\/pv\/341\/0SL0HAR0CG20THKIWQWYVCPQ20.jpg",
            "sources": [
                {
                    "file": "\/pv\/hls\/0SL0HAR0CG20THKIWQWYVCPQ20.m3u8?in=::49d877ee106f253f2a0fdec66995b8d1::1773442579::su",
                    "label": "Auto",
                    "type": "application\/vnd.apple.mpegurl"
                }
            ],
            "image1": "https:\/\/imgcdn.kim\/pv\/c\/0SL0HAR0CG20THKIWQWYVCPQ20.jpg"
        }
    ],
    "0SGKU1AGOM2JAKVOU97JZ3FJU5": [
        {
            "title": "",
            "image2": "https:\/\/imgcdn.kim\/pv\/341\/0SGKU1AGOM2JAKVOU97JZ3FJU5.jpg",
            "sources": [
                {
                    "file": "\/pv\/hls\/0SGKU1AGOM2JAKVOU97JZ3FJU5.m3u8?in=::739632cd71e74a9f4b8d26ee5b8a61ba::1773442579::su",
                    "label": "Auto",
                    "type": "application\/vnd.apple.mpegurl"
                }
            ],
            "image1": "https:\/\/imgcdn.kim\/pv\/c\/0SGKU1AGOM2JAKVOU97JZ3FJU5.jpg"
        }
    ],
    "0LI59H74YQS3JFS620EE7OXZZK": [
        {
            "title": "",
            "image2": "https:\/\/imgcdn.kim\/pv\/341\/0LI59H74YQS3JFS620EE7OXZZK.jpg",
            "sources": [
                {
                    "file": "\/pv\/hls\/0LI59H74YQS3JFS620EE7OXZZK.m3u8?in=::484d68287971029e32ea940f7060857b::1773442579::su",
                    "label": "Auto",
                    "type": "application\/vnd.apple.mpegurl"
                }
            ],
            "image1": "https:\/\/imgcdn.kim\/pv\/c\/0LI59H74YQS3JFS620EE7OXZZK.jpg"
        }
    ],
    "0MTNZS3FJR9SBSDWW8LLNEJLTC": [
        {
            "title": "",
            "image2": "https:\/\/imgcdn.kim\/pv\/341\/0MTNZS3FJR9SBSDWW8LLNEJLTC.jpg",
            "sources": [
                {
                    "file": "\/pv\/hls\/0MTNZS3FJR9SBSDWW8LLNEJLTC.m3u8?in=::56b5fc7def7f5893c5a31e15e5bdea00::1773442580::su",
                    "label": "Auto",
                    "type": "application\/vnd.apple.mpegurl"
                }
            ],
            "image1": "https:\/\/imgcdn.kim\/pv\/c\/0MTNZS3FJR9SBSDWW8LLNEJLTC.jpg"
        }
    ],
    "0HJHO3K9D0Y9F2DGA5M2PQQJQ9": [
        {
            "title": "",
            "image2": "https:\/\/imgcdn.kim\/pv\/341\/0HJHO3K9D0Y9F2DGA5M2PQQJQ9.jpg",
            "sources": [
                {
                    "file": "\/pv\/hls\/0HJHO3K9D0Y9F2DGA5M2PQQJQ9.m3u8?in=::0a48a1717124ba7e46cc7c795419ab2b::1773442580::su",
                    "label": "Auto",
                    "type": "application\/vnd.apple.mpegurl"
                }
            ],
            "image1": "https:\/\/imgcdn.kim\/pv\/c\/0HJHO3K9D0Y9F2DGA5M2PQQJQ9.jpg"
        }
    ],
    "0NWCG98163Y8QZYWF0S63HE5WT": [
        {
            "title": "",
            "image2": "https:\/\/imgcdn.kim\/pv\/341\/0NWCG98163Y8QZYWF0S63HE5WT.jpg",
            "sources": [
                {
                    "file": "\/pv\/hls\/0NWCG98163Y8QZYWF0S63HE5WT.m3u8?in=::2304efb5eedee9391d2c20ae11d4de4c::1773442580::su",
                    "label": "Auto",
                    "type": "application\/vnd.apple.mpegurl"
                }
            ],
            "image1": "https:\/\/imgcdn.kim\/pv\/c\/0NWCG98163Y8QZYWF0S63HE5WT.jpg"
        }
    ],
    "0L4UWE8GOWIRCAFEKAU2A3RSR3": [
        {
            "title": "",
            "image2": "https:\/\/imgcdn.kim\/pv\/341\/0L4UWE8GOWIRCAFEKAU2A3RSR3.jpg",
            "sources": [
                {
                    "file": "\/pv\/hls\/0L4UWE8GOWIRCAFEKAU2A3RSR3.m3u8?in=::a4d2d7279c3958f0c61c0490889a7b41::1773442580::su",
                    "label": "Auto",
                    "type": "application\/vnd.apple.mpegurl"
                }
            ],
            "image1": "https:\/\/imgcdn.kim\/pv\/c\/0L4UWE8GOWIRCAFEKAU2A3RSR3.jpg"
        }
    ],
    "0GGNRYFCQVN838QBG4XJHNJUIQ": [
        {
            "title": "",
            "image2": "https:\/\/imgcdn.kim\/pv\/341\/0GGNRYFCQVN838QBG4XJHNJUIQ.jpg",
            "sources": [
                {
                    "file": "\/pv\/hls\/0GGNRYFCQVN838QBG4XJHNJUIQ.m3u8?in=::adc5bed14abcd537ed8fb9ccc2c63358::1773442581::su",
                    "label": "Auto",
                    "type": "application\/vnd.apple.mpegurl"
                }
            ],
            "image1": "https:\/\/imgcdn.kim\/pv\/c\/0GGNRYFCQVN838QBG4XJHNJUIQ.jpg"
        }
    ],
    "0O3YHII1U1VP6SI8J06B7OYAT6": [
        {
            "title": "",
            "image2": "https:\/\/imgcdn.kim\/pv\/341\/0O3YHII1U1VP6SI8J06B7OYAT6.jpg",
            "sources": [
                {
                    "file": "\/pv\/hls\/0O3YHII1U1VP6SI8J06B7OYAT6.m3u8?in=::55d2eef06fcc4206a1fea94515683fa2::1773442581::su",
                    "label": "Auto",
                    "type": "application\/vnd.apple.mpegurl"
                }
            ],
            "image1": "https:\/\/imgcdn.kim\/pv\/c\/0O3YHII1U1VP6SI8J06B7OYAT6.jpg"
        }
    ]
}