[
    {
        "id": "edge2\/tsports",
        "name": "T Sports",
        "cate": "sports",
        "logo": "https:\/\/nettv.fun\/playlist\/bdix\/logo\/102.png",
        "stream": "https:\/\/edge2.roarzone.info:8443\/roarzone\/edge2\/tsports\/index.m3u8?token=35c9973e3407be1aeb36ec8ebc6f7d54cb6d2358-04168e47b4cab2dd16f0b49c27b9e6d0-1767656667-1767653067"
    },
    {
        "id": "bk\/25",
        "name": "Star sports 1",
        "cate": "sports",
        "logo": "https:\/\/nettv.fun\/playlist\/bdix\/logo\/25.png",
        "stream": "https:\/\/edge2.roarzone.info:8443\/roarzone\/bk\/25\/index.m3u8?token=571474b7cbfdd9b826a9712bc4902b8088b7fd96-d2b50032d625cb03eeb261885eaf857b-1767656668-1767653068"
    },
    {
        "id": "bk\/26",
        "name": "Star sports 2",
        "cate": "sports",
        "logo": "https:\/\/nettv.fun\/playlist\/bdix\/logo\/26.png",
        "stream": "https:\/\/edge2.roarzone.info:8443\/roarzone\/bk\/26\/index.m3u8?token=8f4ee37906db94bb758dd334d81bd4c377427374-b49405b81bd3827704d1c94ffbde225c-1767656670-1767653070"
    },
    {
        "id": "bk\/1",
        "name": "Gazi tv",
        "cate": "sports",
        "logo": "https:\/\/nettv.fun\/playlist\/bdix\/logo\/1.png",
        "stream": "https:\/\/edge2.roarzone.info:8443\/roarzone\/bk\/1\/index.m3u8?token=3f39a7571eb8113f0eff7002173df21f3815bf0d-6f4e4c71089200a8247627fcdb1e41eb-1767656670-1767653070"
    },
    {
        "id": "bk\/20",
        "name": "Sony ten 1",
        "cate": "sports",
        "logo": "https:\/\/nettv.fun\/playlist\/bdix\/logo\/20.png",
        "stream": "https:\/\/edge2.roarzone.info:8443\/roarzone\/bk\/20\/index.m3u8?token=fe8de1cad491f44afcaeadbb7e42a121381d2db9-46c03548fd06abf69a7eb38ce3a54798-1767656672-1767653072"
    },
    {
        "id": "bk\/21",
        "name": "Sony ten 2",
        "cate": "sports",
        "logo": "https:\/\/nettv.fun\/playlist\/bdix\/logo\/21.png",
        "stream": "https:\/\/edge2.roarzone.info:8443\/roarzone\/bk\/21\/index.m3u8?token=16d2056bf52b7a48c0ed05bbd49c2cabb013f133-ae54592f9828a3be8473f6eb51f2fa60-1767656673-1767653073"
    },
    {
        "id": "bk\/22",
        "name": "Sony ten 3",
        "cate": "sports",
        "logo": "https:\/\/nettv.fun\/playlist\/bdix\/logo\/22.png",
        "stream": "https:\/\/edge2.roarzone.info:8443\/roarzone\/bk\/22\/index.m3u8?token=855849ce3d9c770429eae9021c228bc84355ccb9-d3eb0d9e109ccf2cb918d5855b30b1f7-1767656674-1767653074"
    },
    {
        "id": "bk\/24",
        "name": "Sony six",
        "cate": "sports",
        "logo": "https:\/\/nettv.fun\/playlist\/bdix\/logo\/24.png",
        "stream": "https:\/\/edge2.roarzone.info:8443\/roarzone\/bk\/24\/index.m3u8?token=0d5f57df225bcfb782d9122cb59f8ce70094c431-a5aca14a549953078f27003286d14277-1767656675-1767653075"
    },
    {
        "id": "toffee\/euro_sports_hd",
        "name": "Euro sports",
        "cate": "sports",
        "logo": "https:\/\/nettv.fun\/playlist\/bdix\/logo\/euro_sports_hd.png",
        "stream": "https:\/\/edge2.roarzone.info:8443\/roarzone\/toffee\/euro_sports_hd\/index.m3u8?token=21e561c9c2c7c116cee7ad19fdd68efe8d009a31-146febd4c5f2c7cdec5b1443b6aded41-1767656676-1767653076"
    },
    {
        "id": "toffee\/ten_cricket",
        "name": "Ten cricket",
        "cate": "sports",
        "logo": "https:\/\/nettv.fun\/playlist\/bdix\/logo\/ten_cricket.png",
        "stream": "https:\/\/edge2.roarzone.info:8443\/roarzone\/toffee\/ten_cricket\/index.m3u8?token=09442d55a42a3282a50a88b80afbd8bd35c995a1-ae778992436a7341f41d87688116a19c-1767656677-1767653077"
    },
    {
        "id": "bk\/28",
        "name": "Star sports select 2",
        "cate": "sports",
        "logo": "https:\/\/nettv.fun\/playlist\/bdix\/logo\/28.png",
        "stream": "https:\/\/edge2.roarzone.info:8443\/roarzone\/bk\/28\/index.m3u8?token=1447a06038ea5ca54d29e55c1fa2185b3f30149e-fa70e8c8ec2cf0e7e6d67337c370ecfb-1767656678-1767653078"
    },
    {
        "id": "bk\/27",
        "name": "Star sports select 1",
        "cate": "sports",
        "logo": "https:\/\/nettv.fun\/playlist\/bdix\/logo\/27.png",
        "stream": "https:\/\/edge2.roarzone.info:8443\/roarzone\/bk\/27\/index.m3u8?token=18caefd980671e22f6e255f2645ea55556c16b2a-4912c62ccd532c54b4741fafc8d6d157-1767656679-1767653079"
    },
    {
        "id": "bk\/dubai-sports",
        "name": "Dubai sports",
        "cate": "sports",
        "logo": "https:\/\/nettv.fun\/playlist\/bdix\/logo\/dubai-sports.png",
        "stream": "https:\/\/edge2.roarzone.info:8443\/roarzone\/bk\/dubai-sports\/index.m3u8?token=07fe17c355e88774b1f3b26d8d674d8173d184f7-eef7939f6bc88c43966ea22cef617efe-1767656680-1767653080"
    },
    {
        "id": "bk\/30",
        "name": "Star jalsha",
        "cate": "inbangla",
        "logo": "https:\/\/nettv.fun\/playlist\/bdix\/logo\/30.png",
        "stream": "https:\/\/edge2.roarzone.info:8443\/roarzone\/bk\/30\/index.m3u8?token=0ea248439e3efe7cbe510d7e8e3be076f36742b3-47faf7315c3cbf063397fb3539d057b8-1767656681-1767653081"
    },
    {
        "id": "bk\/31",
        "name": "Star jalsha movies",
        "cate": "inbangla",
        "logo": "https:\/\/nettv.fun\/playlist\/bdix\/logo\/31.png",
        "stream": "https:\/\/edge2.roarzone.info:8443\/roarzone\/bk\/31\/index.m3u8?token=d3caaddc7ec5d790c7837fa64e81282364224b5d-8a116970450c762bdc62ccb42b41d90e-1767656682-1767653082"
    },
    {
        "id": "bk\/34",
        "name": "Zee bangla",
        "cate": "inbangla",
        "logo": "https:\/\/nettv.fun\/playlist\/bdix\/logo\/34.png",
        "stream": "https:\/\/edge2.roarzone.info:8443\/roarzone\/bk\/34\/index.m3u8?token=80c8b3e9acb09a8cf28522023390a03eaf718782-87bfed8741f3eb8a2dfb8b9fbefe2fdc-1767656683-1767653083"
    },
    {
        "id": "bk\/29",
        "name": "Zee bangla cinema",
        "cate": "inbangla",
        "logo": "https:\/\/nettv.fun\/playlist\/bdix\/logo\/29.png",
        "stream": "https:\/\/edge2.roarzone.info:8443\/roarzone\/bk\/29\/index.m3u8?token=76114b239b4d3f8a57642ab85b26aa1ed2adef67-91567686079e783e1feb7226585dbd67-1767656684-1767653084"
    },
    {
        "id": "bk\/66",
        "name": "Colors bangla",
        "cate": "inbangla",
        "logo": "https:\/\/nettv.fun\/playlist\/bdix\/logo\/66.png",
        "stream": "https:\/\/edge2.roarzone.info:8443\/roarzone\/bk\/66\/index.m3u8?token=8eada860d996152c521008861a2c1b7397d7a9f9-0c4f376cb69c5be2ac069572561b7b0e-1767656685-1767653085"
    },
    {
        "id": "bk\/33",
        "name": "Sony aath",
        "cate": "inbangla",
        "logo": "https:\/\/nettv.fun\/playlist\/bdix\/logo\/33.png",
        "stream": "https:\/\/edge2.roarzone.info:8443\/roarzone\/bk\/33\/index.m3u8?token=79198658f5697055cd12e7696357060258061466-39efdc8f07d6a23ad0afc7e2708eb58c-1767656686-1767653086"
    },
    {
        "id": "bk\/72",
        "name": "Star gold select",
        "cate": "hindi",
        "logo": "https:\/\/nettv.fun\/playlist\/bdix\/logo\/75.png",
        "stream": "https:\/\/edge2.roarzone.info:8443\/roarzone\/bk\/72\/index.m3u8?token=dde6f45ca23c317924bf3d8c1716b795a99ba239-59b864e361d5f08ffa7584a4eb4c1c93-1767656687-1767653087"
    },
    {
        "id": "bk\/38",
        "name": "Sony tv",
        "cate": "hindi",
        "logo": "https:\/\/nettv.fun\/playlist\/bdix\/logo\/38.png",
        "stream": "https:\/\/edge2.roarzone.info:8443\/roarzone\/bk\/38\/index.m3u8?token=1cc6d90b04fb8810287c5062a1bb84423ac9042c-e6426d53ce9b24bb4591257f37924964-1767656688-1767653088"
    },
    {
        "id": "bk\/77",
        "name": "Sony max",
        "cate": "hindi",
        "logo": "https:\/\/nettv.fun\/playlist\/bdix\/logo\/sonymax.png",
        "stream": "https:\/\/edge2.roarzone.info:8443\/roarzone\/bk\/77\/index.m3u8?token=2a2e63e084f2d33c1870aa13480183306321705d-b1b9ad20700e42e8f8cccf7c794290cc-1767656689-1767653089"
    },
    {
        "id": "toffee\/sony_max_hd",
        "name": "Sony max hd",
        "cate": "hindi",
        "logo": "https:\/\/nettv.fun\/playlist\/bdix\/logo\/sonymaxhd.png",
        "stream": "https:\/\/edge2.roarzone.info:8443\/roarzone\/toffee\/sony_max_hd\/index.m3u8?token=09cbcfa633a9de17b8c254491fa5952410f6af90-0d8d8d12977e1b3492c729e0cb026d69-1767656690-1767653090"
    },
    {
        "id": "toffee\/sonymax_2",
        "name": "Sony max 2",
        "cate": "hindi",
        "logo": "https:\/\/nettv.fun\/playlist\/bdix\/logo\/sonymax2.png",
        "stream": "https:\/\/edge2.roarzone.info:8443\/roarzone\/toffee\/sonymax_2\/index.m3u8?token=154271f3aef2eb3b31a25cbc4495c9743dce8d04-ddaac4baba0d718a4c1dfe493610f244-1767656691-1767653091"
    },
    {
        "id": "bk\/68",
        "name": "Colors",
        "cate": "hindi",
        "logo": "https:\/\/nettv.fun\/playlist\/bdix\/logo\/68.png",
        "stream": "https:\/\/edge2.roarzone.info:8443\/roarzone\/bk\/68\/index.m3u8?token=1eac8fc36ebd925e05087841b8a9ac4101254e32-ae9f45c3a37b3e01413ed3c095453209-1767656692-1767653092"
    },
    {
        "id": "bk\/40",
        "name": "Zee tv",
        "cate": "hindi",
        "logo": "https:\/\/nettv.fun\/playlist\/bdix\/logo\/40.png",
        "stream": "https:\/\/edge2.roarzone.info:8443\/roarzone\/bk\/40\/index.m3u8?token=a8d325eca54be7b8c765bcca6ba64c0b0c04befe-76887f82d596a4fcd6208f0bf6376b61-1767656693-1767653093"
    },
    {
        "id": "bk\/76",
        "name": "Zee cinema",
        "cate": "hindi",
        "logo": "https:\/\/nettv.fun\/playlist\/bdix\/logo\/76.png",
        "stream": "https:\/\/edge2.roarzone.info:8443\/roarzone\/bk\/76\/index.m3u8?token=82c1bab2a5c0eda9b1371736c4598a2c1a9d7418-33fdeb48056798fd1cab48438f50f4c5-1767656694-1767653094"
    },
    {
        "id": "toffee\/zee_action",
        "name": "Zee action",
        "cate": "hindi",
        "logo": "https:\/\/nettv.fun\/playlist\/bdix\/logo\/90.png",
        "stream": "https:\/\/edge2.roarzone.info:8443\/roarzone\/toffee\/zee_action\/index.m3u8?token=4bdb85529f0fa19444968704de9a53370bfd7b3d-abe48b0fd61a551a17e7bddf54337784-1767656695-1767653095"
    },
    {
        "id": "toffee\/zee_bollywood",
        "name": "Zee bollywood",
        "cate": "hindi",
        "logo": "https:\/\/nettv.fun\/playlist\/bdix\/logo\/94.png",
        "stream": "https:\/\/edge2.roarzone.info:8443\/roarzone\/toffee\/zee_bollywood\/index.m3u8?token=53d804a1da49558c21ee616435ffc729e0f2f8e5-9b5839a103c40d7d742f72f344d8f14b-1767656696-1767653096"
    },
    {
        "id": "bk\/67",
        "name": "Star plus",
        "cate": "hindi",
        "logo": "https:\/\/nettv.fun\/playlist\/bdix\/logo\/67.png",
        "stream": "https:\/\/edge2.roarzone.info:8443\/roarzone\/bk\/67\/index.m3u8?token=2c01e52668a394970a42b4f11b5e5d3087861aac-1dad7c0b7291aa61ccacfca74efe6ebb-1767656697-1767653097"
    },
    {
        "id": "bk\/74",
        "name": "And tv hd",
        "cate": "hindi",
        "logo": "https:\/\/nettv.fun\/playlist\/bdix\/logo\/74.png",
        "stream": "https:\/\/edge2.roarzone.info:8443\/roarzone\/bk\/74\/index.m3u8?token=1191e08b861c32ef8361daae89391636f741d977-ef0af108d7f63894a72ade3a8e935dac-1767656698-1767653098"
    },
    {
        "id": "bk\/100",
        "name": "And pictures",
        "cate": "hindi",
        "logo": "https:\/\/nettv.fun\/playlist\/bdix\/logo\/100.png",
        "stream": "https:\/\/edge2.roarzone.info:8443\/roarzone\/bk\/100\/index.m3u8?token=e0f6bdc1cd300d5b3d1457d343f49b3550ddbc06-1f2375ad7a6b2a631703e317629b42b3-1767656699-1767653099"
    },
    {
        "id": "toffee\/zee_anmol",
        "name": "Zee-Anmol",
        "cate": "hindi",
        "logo": "https:\/\/nettv.fun\/playlist\/bdix\/logo\/zee-anmol.png",
        "stream": "https:\/\/edge2.roarzone.info:8443\/roarzone\/toffee\/zee_anmol\/index.m3u8?token=6b72ff763345df72352698e4ebbed5e96d2986c6-52677d69ee6fc3ffbf37d3ffeb8d81de-1767656700-1767653100"
    },
    {
        "id": "toffee\/hum_tv",
        "name": "Hum Tv",
        "cate": "hindi",
        "logo": "https:\/\/nettv.fun\/playlist\/bdix\/logo\/humtv.png",
        "stream": "https:\/\/edge2.roarzone.info:8443\/roarzone\/toffee\/hum_tv\/index.m3u8?token=407c95c2023801c0cc17a55644ad67aaa436f77d-39fce4ef22975308896dc1dd8b4e254d-1767656701-1767653101"
    },
    {
        "id": "toffee\/hum_masala",
        "name": "Hum Masala",
        "cate": "hindi",
        "logo": "https:\/\/nettv.fun\/playlist\/bdix\/logo\/hummasala.png",
        "stream": "https:\/\/edge2.roarzone.info:8443\/roarzone\/toffee\/hum_masala\/index.m3u8?token=01eb93bd812529304a1075f58172a99316188aaf-a9661525d77fdc4a3f4170570dd8fdf5-1767656702-1767653102"
    },
    {
        "id": "toffee\/hum_sitaray",
        "name": "Hum Sitarey",
        "cate": "hindi",
        "logo": "https:\/\/nettv.fun\/playlist\/bdix\/logo\/humsitarey.png",
        "stream": "https:\/\/edge2.roarzone.info:8443\/roarzone\/toffee\/hum_sitaray\/index.m3u8?token=d76d7a7674a4e7c6bade359725f65c6d2e97c7c4-6233d2ad5f76ad7951006b5e0397e895-1767656703-1767653103"
    },
    {
        "id": "toffee\/b4u_movies",
        "name": "B4u Movies",
        "cate": "hindi",
        "logo": "https:\/\/nettv.fun\/playlist\/bdix\/logo\/b4umovies.png",
        "stream": "https:\/\/edge2.roarzone.info:8443\/roarzone\/toffee\/b4u_movies\/index.m3u8?token=dd35388051f405fb20a3016b3edbaf16c97f062d-ca76f4bfc6292c20321a16cd8257ef96-1767656704-1767653104"
    },
    {
        "id": "bk\/58",
        "name": "Gaan Bangla",
        "cate": "music",
        "logo": "https:\/\/nettv.fun\/playlist\/bdix\/logo\/58.png",
        "stream": "https:\/\/edge2.roarzone.info:8443\/roarzone\/bk\/58\/index.m3u8?token=5d83efb2deea5f544cbbacacc27dda908107f9f3-64481304d5b6dbcf9756589be97a379d-1767656705-1767653105"
    },
    {
        "id": "bk\/48",
        "name": "9xm",
        "cate": "music",
        "logo": "https:\/\/nettv.fun\/playlist\/bdix\/logo\/48.png",
        "stream": "https:\/\/edge2.roarzone.info:8443\/roarzone\/bk\/48\/index.m3u8?token=0d3644eed6b57744a03b637387f713c9d15b4cba-f673e01519e8ea888e8dcfa7c378b2f1-1767656706-1767653106"
    },
    {
        "id": "toffee\/Zing",
        "name": "Zing",
        "cate": "music",
        "logo": "https:\/\/nettv.fun\/playlist\/bdix\/logo\/93.png",
        "stream": "https:\/\/edge2.roarzone.info:8443\/roarzone\/toffee\/Zing\/index.m3u8?token=c971adc5e56803ab5b97986f8e5f5fcf61dab165-f52c370d80b2c2ad5ce6a57f89e28869-1767656707-1767653107"
    },
    {
        "id": "toffee\/b4u_music",
        "name": "B4u Music",
        "cate": "music",
        "logo": "https:\/\/nettv.fun\/playlist\/bdix\/logo\/b4umusic.png",
        "stream": "https:\/\/edge2.roarzone.info:8443\/roarzone\/toffee\/b4u_music\/index.m3u8?token=9c7d4581379d9d23f8752b29774cdb3097dc4607-3734887a259c8c180ed8369e58e2d827-1767656708-1767653108"
    },
    {
        "id": "bk\/83",
        "name": "Discovery hd",
        "cate": "documentary",
        "logo": "https:\/\/nettv.fun\/playlist\/bdix\/logo\/43.png",
        "stream": "https:\/\/edge2.roarzone.info:8443\/roarzone\/bk\/83\/index.m3u8?token=bfa1a97074c79a76b2619741659da5b2df23cbd6-66ff6f0a9e611c8b890189a3d5dbec36-1767656709-1767653109"
    },
    {
        "id": "toffee\/discovery_science",
        "name": "Discovery science",
        "cate": "documentary",
        "logo": "https:\/\/nettv.fun\/playlist\/bdix\/logo\/discoveryscience.png",
        "stream": "https:\/\/edge2.roarzone.info:8443\/roarzone\/toffee\/discovery_science\/index.m3u8?token=23116d2833b0becc0ec2e93c36c95c445a678d6f-33ff44527f250830393504bba1f0383a-1767656710-1767653110"
    },
    {
        "id": "toffee\/discovery_turbo",
        "name": "Discovery turbo",
        "cate": "documentary",
        "logo": "https:\/\/nettv.fun\/playlist\/bdix\/logo\/discoveryturbo.png",
        "stream": "https:\/\/edge2.roarzone.info:8443\/roarzone\/toffee\/discovery_turbo\/index.m3u8?token=a4dc96c63a86ad59c79c6dda0c8307545a9d6bb1-6031ee77d73a636fbed0d5a3b23a55a7-1767656711-1767653111"
    },
    {
        "id": "toffee\/discovary_investigation_hd",
        "name": "Discovery hd investigation",
        "cate": "documentary",
        "logo": "https:\/\/nettv.fun\/playlist\/bdix\/logo\/discoveryhdInvestigation.png",
        "stream": "https:\/\/edge2.roarzone.info:8443\/roarzone\/toffee\/discovary_investigation_hd\/index.m3u8?token=74742afe47e78af480794c3e684a6dc357fc5144-019276b960ecd138c04c0ff3a3a588cb-1767656712-1767653112"
    },
    {
        "id": "toffee\/cnn",
        "name": "Cnn",
        "cate": "documentary",
        "logo": "https:\/\/nettv.fun\/playlist\/bdix\/logo\/cnn.png",
        "stream": "https:\/\/edge2.roarzone.info:8443\/roarzone\/toffee\/cnn\/index.m3u8?token=609a23180ad48470f159753fc8dd7ce0ef78c4d0-de7fa798f165bb40b889bc58dd839a5d-1767656713-1767653113"
    },
    {
        "id": "bk\/44",
        "name": "Sony bbc earth hd",
        "cate": "documentary",
        "logo": "https:\/\/nettv.fun\/playlist\/bdix\/logo\/44.png",
        "stream": "https:\/\/edge2.roarzone.info:8443\/roarzone\/bk\/44\/index.m3u8?token=eb6a37934ffa6802643618982e673694296b3743-8d8383cbcb3fadca9a14993dfb6231c5-1767656714-1767653114"
    },
    {
        "id": "bk\/35",
        "name": "Natgeo",
        "cate": "documentary",
        "logo": "https:\/\/nettv.fun\/playlist\/bdix\/logo\/35.png",
        "stream": "https:\/\/edge2.roarzone.info:8443\/roarzone\/bk\/35\/index.m3u8?token=d6c11d440036ac7b588fcb89a02361983cfae7df-e8219de06202163cae8ff4577cc4c657-1767656715-1767653115"
    },
    {
        "id": "toffee\/animal_planet_hd",
        "name": "Animal planet",
        "cate": "documentary",
        "logo": "https:\/\/nettv.fun\/playlist\/bdix\/logo\/animalplanet.png",
        "stream": "https:\/\/edge2.roarzone.info:8443\/roarzone\/toffee\/animal_planet_hd\/index.m3u8?token=a2d084f143aba351f99befd3a5d23c4f054c1bf0-eab29745c8d09fa93f3b4d19c73a7798-1767656716-1767653116"
    },
    {
        "id": "bk\/79",
        "name": "Cartoon network",
        "cate": "kids",
        "logo": "https:\/\/nettv.fun\/playlist\/bdix\/logo\/79.png",
        "stream": "https:\/\/edge2.roarzone.info:8443\/roarzone\/bk\/79\/index.m3u8?token=ba61bd2c21c9934d92493bb70fadc72ea81b0cb1-268eb8f60a63f893ce41f746539b6223-1767656717-1767653117"
    },
    {
        "id": "bk\/55",
        "name": "Nick",
        "cate": "kids",
        "logo": "https:\/\/nettv.fun\/playlist\/bdix\/logo\/55.png",
        "stream": "https:\/\/edge2.roarzone.info:8443\/roarzone\/bk\/55\/index.m3u8?token=f2d830faa63d62452dfa3c795323dd9f3c14ba90-801d9aecbcd61b05228beec6cc0419ad-1767656718-1767653118"
    },
    {
        "id": "toffee\/pogo_sd",
        "name": "Pogo",
        "cate": "kids",
        "logo": "https:\/\/nettv.fun\/playlist\/bdix\/logo\/pogo.png",
        "stream": "https:\/\/edge2.roarzone.info:8443\/roarzone\/toffee\/pogo_sd\/index.m3u8?token=0f8cace6cba5053de302d0307ac3393e53259a69-600f399c01826375e9b1b6b3beee0551-1767656719-1767653119"
    },
    {
        "id": "toffee\/discovery_kids",
        "name": "Discovery kids",
        "cate": "kids",
        "logo": "https:\/\/nettv.fun\/playlist\/bdix\/logo\/discoverykids.png",
        "stream": "https:\/\/edge2.roarzone.info:8443\/roarzone\/toffee\/discovery_kids\/index.m3u8?token=9302f801c0072c2d1da5eb528beb98c3a3b3981b-b68ff647b4b1474dd2f0e1aa9247c86d-1767656720-1767653120"
    },
    {
        "id": "toffee\/sonyyay",
        "name": "Sony Yay",
        "cate": "kids",
        "logo": "https:\/\/nettv.fun\/playlist\/bdix\/logo\/sonyyay.png",
        "stream": "https:\/\/edge2.roarzone.info:8443\/roarzone\/toffee\/sonyyay\/index.m3u8?token=f72d37270072cc4617a8111771967359ea9e9d86-4f2da708ad506d6f6da7c13d979ec5f6-1767656721-1767653121"
    },
    {
        "id": "bk\/65",
        "name": "ekushy tv",
        "cate": "bangla",
        "logo": "https:\/\/nettv.fun\/playlist\/bdix\/logo\/65.png",
        "stream": "https:\/\/edge2.roarzone.info:8443\/roarzone\/bk\/65\/index.m3u8?token=a23b6c108c68169d57d8831c531a2d55f615f3af-e910970841c0039eb14deb76af869692-1767656722-1767653122"
    },
    {
        "id": "bk\/13",
        "name": "Jamuna tv",
        "cate": "bangla",
        "logo": "https:\/\/nettv.fun\/playlist\/bdix\/logo\/13.png",
        "stream": "https:\/\/edge2.roarzone.info:8443\/roarzone\/bk\/13\/index.m3u8?token=e7b52c14e5cc87fc94305d0daa0101663a214051-bce747ae843634b4cf5a0554accb86c2-1767656723-1767653123"
    },
    {
        "id": "bk\/59",
        "name": "Nagorik tv",
        "cate": "bangla",
        "logo": "https:\/\/nettv.fun\/playlist\/bdix\/logo\/59.png",
        "stream": "https:\/\/edge2.roarzone.info:8443\/roarzone\/bk\/59\/index.m3u8?token=20af3b8b1bec50ed5cd5a1c3d231386b5447920f-318aa2a4e80ae54ab504526196a8cd1f-1767656724-1767653124"
    },
    {
        "id": "edge\/asian-tv",
        "name": "Asian tv",
        "cate": "bangla",
        "logo": "https:\/\/nettv.fun\/playlist\/bdix\/logo\/62.png",
        "stream": "https:\/\/edge2.roarzone.info:8443\/roarzone\/edge\/asian-tv\/index.m3u8?token=f3bef8a53c44de3ce09f20cd38325cf28e3ccc46-2be5fcb28de747664b9430de5d75afb9-1767656725-1767653125"
    },
    {
        "id": "bk\/2",
        "name": "Atn Bangla",
        "cate": "bangla",
        "logo": "https:\/\/nettv.fun\/playlist\/bdix\/logo\/2.png",
        "stream": "https:\/\/edge2.roarzone.info:8443\/roarzone\/bk\/2\/index.m3u8?token=2397d02f0be10f302ffa60bac0660e6a01f8e224-0d1c4a10b76c98009106d3d93bae2f81-1767656726-1767653126"
    },
    {
        "id": "bk\/49",
        "name": "Atn News",
        "cate": "bangla",
        "logo": "https:\/\/nettv.fun\/playlist\/bdix\/logo\/49.png",
        "stream": "https:\/\/edge2.roarzone.info:8443\/roarzone\/bk\/49\/index.m3u8?token=b347799d4100425618fa84ced2481c092f834c99-fe76586d66a1441400dd83eed21e4a28-1767656727-1767653127"
    },
    {
        "id": "bk\/3",
        "name": "Banglavision Tv",
        "cate": "bangla",
        "logo": "https:\/\/nettv.fun\/playlist\/bdix\/logo\/3.png",
        "stream": "https:\/\/edge2.roarzone.info:8443\/roarzone\/bk\/3\/index.m3u8?token=ac4d63b383f48484e9043f75358c3a5b8268bb3a-6ce6555a2f4af7574ec54a18c5db89ae-1767656728-1767653128"
    },
    {
        "id": "bk\/19",
        "name": "Bangla Tv",
        "cate": "bangla",
        "logo": "https:\/\/nettv.fun\/playlist\/bdix\/logo\/19.png",
        "stream": "https:\/\/edge2.roarzone.info:8443\/roarzone\/bk\/19\/index.m3u8?token=d306f6d4e2bb8f4481f63cd437b10debb8b0478d-f96566ac087a60f1a52485f52243301f-1767656729-1767653129"
    },
    {
        "id": "bk\/61",
        "name": "Boishakhi Tv",
        "cate": "bangla",
        "logo": "https:\/\/nettv.fun\/playlist\/bdix\/logo\/61.png",
        "stream": "https:\/\/edge2.roarzone.info:8443\/roarzone\/bk\/61\/index.m3u8?token=08a1af81518a444c06c1fac765497c5e2b2b471f-7952cab07e060479ce2c795a7de23a70-1767656730-1767653130"
    },
    {
        "id": "bk\/53",
        "name": "Btv",
        "cate": "bangla",
        "logo": "https:\/\/nettv.fun\/playlist\/bdix\/logo\/53.png",
        "stream": "https:\/\/edge2.roarzone.info:8443\/roarzone\/bk\/53\/index.m3u8?token=30402760d2e005122928d4d8cccf946975b815d0-585c3a9d9754ba099502269909f44a5b-1767656731-1767653131"
    },
    {
        "id": "bk\/84",
        "name": "Btv world",
        "cate": "bangla",
        "logo": "https:\/\/nettv.fun\/playlist\/bdix\/logo\/84.png",
        "stream": "https:\/\/edge2.roarzone.info:8443\/roarzone\/bk\/84\/index.m3u8?token=32f2baeaf8d4b1f4f8040df38f28328c74d36083-170a28266af709baf5fe5885b588b79b-1767656732-1767653132"
    },
    {
        "id": "bk\/5",
        "name": "Channel 24",
        "cate": "bangla",
        "logo": "https:\/\/nettv.fun\/playlist\/bdix\/logo\/5.png",
        "stream": "https:\/\/edge2.roarzone.info:8443\/roarzone\/bk\/5\/index.m3u8?token=eeeefcd9057a0ecc748a785cd8711bfe8b2e6cd3-0b24f467baac36d0cfcad361869c2a83-1767656733-1767653133"
    },
    {
        "id": "bk\/4",
        "name": "Channel 9",
        "cate": "bangla",
        "logo": "https:\/\/nettv.fun\/playlist\/bdix\/logo\/4.png",
        "stream": "https:\/\/edge2.roarzone.info:8443\/roarzone\/bk\/4\/index.m3u8?token=33dcd0617770809835417c6d266fa803a61cd378-7d792678a4478e472410412610925a6b-1767656734-1767653134"
    },
    {
        "id": "bk\/6",
        "name": "Channel i",
        "cate": "bangla",
        "logo": "https:\/\/nettv.fun\/playlist\/bdix\/logo\/6.png",
        "stream": "https:\/\/edge2.roarzone.info:8443\/roarzone\/bk\/6\/index.m3u8?token=367e1966d02ea11f710ff1a513eb871676a5dd45-15701d0f1e5a0e4331664ff33ee2a6ce-1767656735-1767653135"
    },
    {
        "id": "bk\/7",
        "name": "Dbc News",
        "cate": "bangla",
        "logo": "https:\/\/nettv.fun\/playlist\/bdix\/logo\/7.png",
        "stream": "https:\/\/edge2.roarzone.info:8443\/roarzone\/bk\/7\/index.m3u8?token=83e8263f545c3249667bcdb8c1004611a7d768df-5d6e23a14ccf722f33352c05b829d99f-1767656736-1767653136"
    },
    {
        "id": "bk\/8",
        "name": "Deepto Tv",
        "cate": "bangla",
        "logo": "https:\/\/nettv.fun\/playlist\/bdix\/logo\/8.png",
        "stream": "https:\/\/edge2.roarzone.info:8443\/roarzone\/bk\/8\/index.m3u8?token=c58391d0bcebc00f398ae0f01b88accd23a3db53-64e5759595443576c34e086fa2b2907b-1767656737-1767653137"
    },
    {
        "id": "bk\/9",
        "name": "Desh Tv",
        "cate": "bangla",
        "logo": "https:\/\/nettv.fun\/playlist\/bdix\/logo\/9.png",
        "stream": "https:\/\/edge2.roarzone.info:8443\/roarzone\/bk\/9\/index.m3u8?token=b0f7532aba27d85b9d569b6e56f41ce5bab4432a-dd416f436d2ea28bc64532533832b3dc-1767656738-1767653138"
    },
    {
        "id": "bk\/10",
        "name": "Duronto Tv",
        "cate": "bangla",
        "logo": "https:\/\/nettv.fun\/playlist\/bdix\/logo\/10.png",
        "stream": "https:\/\/edge2.roarzone.info:8443\/roarzone\/bk\/10\/index.m3u8?token=c5da3e244cd701561a6d22c48a8634ff387175ef-003dee55189a37ae9e037955e9aa24c5-1767656739-1767653139"
    },
    {
        "id": "bk\/11",
        "name": "Ekattor Tv",
        "cate": "bangla",
        "logo": "https:\/\/nettv.fun\/playlist\/bdix\/logo\/11.png",
        "stream": "https:\/\/edge2.roarzone.info:8443\/roarzone\/bk\/11\/index.m3u8?token=3f8865eaf5b89f50f5b99f95b4e425b801ccddfb-f7177f846b44fa86e46038ecd57c9b1d-1767656740-1767653140"
    },
    {
        "id": "bk\/12",
        "name": "Independent Tv",
        "cate": "bangla",
        "logo": "https:\/\/nettv.fun\/playlist\/bdix\/logo\/12.png",
        "stream": "https:\/\/edge2.roarzone.info:8443\/roarzone\/bk\/12\/index.m3u8?token=b3068efdc1d37a592576e30f28871b29ecb228e7-ec3a0fab89fb210d3c476bd86218990e-1767656741-1767653141"
    },
    {
        "id": "bk\/51",
        "name": "Maasranga",
        "cate": "bangla",
        "logo": "https:\/\/nettv.fun\/playlist\/bdix\/logo\/51.png",
        "stream": "https:\/\/edge2.roarzone.info:8443\/roarzone\/bk\/51\/index.m3u8?token=ed85c048138a7e57f428bdd527d4991da19a9902-d322cc85b1813a3b3784e738c7e2fe10-1767656742-1767653142"
    },
    {
        "id": "bk\/50",
        "name": "Mohona tv",
        "cate": "bangla",
        "logo": "https:\/\/nettv.fun\/playlist\/bdix\/logo\/50.png",
        "stream": "https:\/\/edge2.roarzone.info:8443\/roarzone\/bk\/50\/index.m3u8?token=14133b0ee521b1711eff7bf5515ec74b1801790f-bf4bf261539ddd33a301045842e2b6db-1767656743-1767653143"
    },
    {
        "id": "bk\/86",
        "name": "Movie Bangla Tv",
        "cate": "bangla",
        "logo": "https:\/\/nettv.fun\/playlist\/bdix\/logo\/86.png",
        "stream": "https:\/\/edge2.roarzone.info:8443\/roarzone\/bk\/86\/index.m3u8?token=3bde2b8888eb6d3ce0409c8ec88a9965bdc85792-d5709bf9db10529d1c5a970e13911234-1767656743-1767653143"
    },
    {
        "id": "bk\/56",
        "name": "My Tv",
        "cate": "bangla",
        "logo": "https:\/\/nettv.fun\/playlist\/bdix\/logo\/56.png",
        "stream": "https:\/\/edge2.roarzone.info:8443\/roarzone\/bk\/56\/index.m3u8?token=f27ebd17889d38b416b4e69a7f834baeed5c5206-83579ccdb1ee554e2d404bd7b7c061f2-1767656744-1767653144"
    },
    {
        "id": "bk\/18",
        "name": "News24",
        "cate": "bangla",
        "logo": "https:\/\/nettv.fun\/playlist\/bdix\/logo\/18.png",
        "stream": "https:\/\/edge2.roarzone.info:8443\/roarzone\/bk\/18\/index.m3u8?token=ccbc4e3fba5ae22709b3d3a538db0080a644cb0e-84e77676b126ea8a3d1cabdfe085efbd-1767656745-1767653145"
    },
    {
        "id": "bk\/54",
        "name": "Ntv",
        "cate": "bangla",
        "logo": "https:\/\/nettv.fun\/playlist\/bdix\/logo\/54.png",
        "stream": "https:\/\/edge2.roarzone.info:8443\/roarzone\/bk\/54\/index.m3u8?token=ee317ab76955d44542872d6c78dd3a08d8bf8322-e411fbf7199a20b767a3855d1edfabe3-1767656746-1767653146"
    },
    {
        "id": "bk\/14",
        "name": "Rtv",
        "cate": "bangla",
        "logo": "https:\/\/nettv.fun\/playlist\/bdix\/logo\/14.png",
        "stream": "https:\/\/edge2.roarzone.info:8443\/roarzone\/bk\/14\/index.m3u8?token=5d8b66a24cf62b610c8a90abc3bf42859a3cec27-2df5b1d2559ab60bba011679a18fca6e-1767656747-1767653147"
    },
    {
        "id": "bk\/15",
        "name": "Sa tv",
        "cate": "bangla",
        "logo": "https:\/\/nettv.fun\/playlist\/bdix\/logo\/15.png",
        "stream": "https:\/\/edge2.roarzone.info:8443\/roarzone\/bk\/15\/index.m3u8?token=2bab4b822178d9239a1a997ce40da1f70cd3f27b-901af914579c6484b1a73522f969ae0f-1767656748-1767653148"
    },
    {
        "id": "bk\/88",
        "name": "Sangsad Tv",
        "cate": "bangla",
        "logo": "https:\/\/nettv.fun\/playlist\/bdix\/logo\/88.png",
        "stream": "https:\/\/edge2.roarzone.info:8443\/roarzone\/bk\/88\/index.m3u8?token=20d7a9300262bba6846ef8f107972f03c2bef525-fad2c287dccb08589d607831cd297453-1767656749-1767653149"
    },
    {
        "id": "bk\/17",
        "name": "Somoy Tv",
        "cate": "bangla",
        "logo": "https:\/\/nettv.fun\/playlist\/bdix\/logo\/17.png",
        "stream": "https:\/\/edge2.roarzone.info:8443\/roarzone\/bk\/17\/index.m3u8?token=51ecc99d60ac062172338ec8f55a5bb658e2e1ff-5bbc7761d815b8cd06a3c1f3de118f04-1767656750-1767653150"
    },
    {
        "id": "ext\/ekhon-tv",
        "name": "Ekhon",
        "cate": "bangla",
        "logo": "https:\/\/nettv.fun\/playlist\/bdix\/logo\/ekhon-tv.jpg",
        "stream": "https:\/\/edge2.roarzone.info:8443\/roarzone\/ext\/ekhon-tv\/index.m3u8?token=be8320aa1e74683ff858cd395aa4e7e8629f7fcd-3b6dd759ce5251eb02182d9f6d158bf0-1767656751-1767653151"
    },
    {
        "id": "ext\/bijoy-tv",
        "name": "Bijoy-tv",
        "cate": "bangla",
        "logo": "https:\/\/nettv.fun\/playlist\/bdix\/logo\/bijoy-tv.jpg",
        "stream": "https:\/\/edge2.roarzone.info:8443\/roarzone\/ext\/bijoy-tv\/index.m3u8?token=11234db1a6b7ca3a81bada49ed52783269bccd2e-a806e4ce3de7673ae8d40c6793d42120-1767656752-1767653152"
    },
    {
        "id": "bk\/starmovies",
        "name": "Star movies",
        "cate": "english",
        "logo": "https:\/\/nettv.fun\/playlist\/bdix\/logo\/starmovies.png",
        "stream": "https:\/\/edge2.roarzone.info:8443\/roarzone\/bk\/starmovies\/index.m3u8?token=d1e12166579392749f232834761fc0e4030fecae-f3843391903e635d4fa9c840eec7057a-1767656753-1767653153"
    },
    {
        "id": "toffee\/zee_cafe_hd",
        "name": "Zee cafe hd",
        "cate": "english",
        "logo": "https:\/\/nettv.fun\/playlist\/bdix\/logo\/69.png",
        "stream": "https:\/\/edge2.roarzone.info:8443\/roarzone\/toffee\/zee_cafe_hd\/index.m3u8?token=5a2ec68cf572cf0919eee46bdea5fa06053920b0-9ace10f45266fc758653c5fcc96c526f-1767656754-1767653154"
    },
    {
        "id": "bk\/41",
        "name": "Sony pix",
        "cate": "english",
        "logo": "https:\/\/nettv.fun\/playlist\/bdix\/logo\/41.png",
        "stream": "https:\/\/edge2.roarzone.info:8443\/roarzone\/bk\/41\/index.m3u8?token=405af7772dbc32eb4cc4274ef5b46291cb8d2026-d44eeda25a915f46ef201b33788ab002-1767656755-1767653155"
    },
    {
        "id": "bk\/85",
        "name": "Dw news",
        "cate": "english",
        "logo": "https:\/\/nettv.fun\/playlist\/bdix\/logo\/85.png",
        "stream": "https:\/\/edge2.roarzone.info:8443\/roarzone\/bk\/85\/index.m3u8?token=7ef1f8658d117edde037d7b3c1838a6fd188ca12-e3b49cb426300fde4ecc2d7f0e34b173-1767656756-1767653156"
    },
    {
        "id": "bk\/89",
        "name": "Al jazeera",
        "cate": "english",
        "logo": "https:\/\/nettv.fun\/playlist\/bdix\/logo\/89.png",
        "stream": "https:\/\/edge2.roarzone.info:8443\/roarzone\/bk\/89\/index.m3u8?token=cdb26970f295c987ee88e91e62c13de8aa92b54d-664eb2ea3d2da582a0757c69cd35b165-1767656757-1767653157"
    }
]